{"optionChain":{"result":[{"underlyingSymbol":"COIN","expirationDates":[1733443200,1734048000,1734652800,1735257600,1735862400,1736467200,1737072000,1740096000,1742515200,1750377600,1755216000,1766102400,1768521600,1778803200,1789689600,1797552000,1799971200],"strikes":[85.0,90.0,95.0,100.0,105.0,110.0,115.0,120.0,125.0,130.0,135.0,140.0,145.0,150.0,155.0,160.0,165.0,170.0,175.0,180.0,185.0,190.0,195.0,200.0,210.0,220.0,230.0,240.0,250.0,260.0,270.0,280.0,290.0,300.0,310.0,320.0,330.0,340.0,350.0,360.0,370.0,380.0,390.0,400.0,410.0,420.0,430.0,440.0,450.0,460.0,470.0,480.0,490.0,500.0,510.0,520.0,530.0,540.0,550.0,570.0,580.0,590.0,600.0,610.0,620.0,630.0,640.0,650.0,660.0],"hasMiniOptions":false,"quote":{"language":"en-US","region":"US","quoteType":"EQUITY","typeDisp":"Equity","quoteSourceName":"Nasdaq Real Time Price","triggerable":true,"customPriceAlertConfidence":"HIGH","currency":"USD","marketState":"POST","earningsTimestamp":1730319120,"earningsTimestampStart":1739444340,"earningsTimestampEnd":1739793600,"earningsCallTimestampStart":1730323800,"earningsCallTimestampEnd":1730323800,"isEarningsDateEstimate":true,"trailingAnnualDividendRate":0.0,"trailingPE":51.341255,"trailingAnnualDividendYield":0.0,"epsTrailingTwelveMonths":5.89,"epsForward":3.57,"epsCurrentYear":5.33838,"priceEpsCurrentYear":56.6464,"sharesOutstanding":204910000,"bookValue":34.872,"fiftyDayAverage":225.3418,"fiftyDayAverageChange":77.0582,"fiftyDayAverageChangePercent":0.3419614,"twoHundredDayAverage":220.5525,"twoHundredDayAverageChange":81.84749,"twoHundredDayAverageChangePercent":0.37110206,"marketCap":79483723776,"forwardPE":84.70588,"priceToBook":8.671713,"sourceInterval":15,"exchangeDataDelayedBy":0,"hasPrePostMarketData":true,"firstTradeDateMilliseconds":1618407000000,"priceHint":2,"postMarketChangePercent":0.42985988,"postMarketTime":1733181182,"postMarketPrice":303.6999,"postMarketChange":1.2998962,"regularMarketChange":6.1999817,"regularMarketTime":1733173201,"regularMarketDayHigh":311.47,"regularMarketDayRange":"299.5 - 311.47","regularMarketDayLow":299.5,"regularMarketVolume":11182566,"regularMarketPreviousClose":296.2,"bid":302.25,"ask":303.46,"bidSize":6,"askSize":4,"fullExchangeName":"NasdaqGS","financialCurrency":"USD","regularMarketOpen":302.621,"averageDailyVolume3Month":12358871,"averageDailyVolume10Day":16813460,"fiftyTwoWeekLowChange":187.88998,"fiftyTwoWeekLowChangePercent":1.6408173,"fiftyTwoWeekRange":"114.51 - 341.75","fiftyTwoWeekHighChange":-39.350006,"fiftyTwoWeekHighChangePercent":-0.115142666,"fiftyTwoWeekLow":114.51,"fiftyTwoWeekHigh":341.75,"fiftyTwoWeekChangePercent":109.93693,"regularMarketChangePercent":2.093174,"regularMarketPrice":302.4,"exchange":"NMS","shortName":"Coinbase Global, Inc.","longName":"Coinbase Global, Inc.","messageBoardId":"finmb_377154867","exchangeTimezoneName":"America/New_York","exchangeTimezoneShortName":"EST","gmtOffSetMilliseconds":-18000000,"market":"us_market","esgPopulated":false,"averageAnalystRating":"2.4 - Buy","tradeable":false,"cryptoTradeable":false,"ipoExpectedDate":"2021-04-14","displayName":"Coinbase Global","symbol":"COIN"},"options":[{"expirationDate":1799971200,"hasMiniOptions":false,"calls":[{"percentChange":{"raw":0.0,"fmt":"0.00%"},"openInterest":{"raw":39,"fmt":"39","longFmt":"39"},"change":{"raw":0.0,"fmt":"0.00"},"strike":{"raw":85.0,"fmt":"85.00"},"inTheMoney":true,"impliedVolatility":{"raw":0.9482732223510743,"fmt":"94.83%"},"volume":{"raw":3,"fmt":"3","longFmt":"3"},"ask":{"raw":238.0,"fmt":"238.00"},"contractSymbol":"COIN270115C00085000","lastTradeDate":{"raw":1732558245,"fmt":"2024-11-25","longFmt":"2024-11-25T18:10"},"contractSize":"REGULAR","expiration":{"raw":1799971200,"fmt":"2027-01-15","longFmt":"2027-01-15T00:00"},"currency":"USD","bid":{"raw":234.0,"fmt":"234.00"},"lastPrice":{"raw":244.0,"fmt":"244.00"}},{"percentChange":{"raw":0.0,"fmt":"0.00%"},"openInterest":{"raw":7,"fmt":"7","longFmt":"7"},"change":{"raw":0.0,"fmt":"0.00"},"strike":{"raw":90.0,"fmt":"90.00"},"inTheMoney":true,"impliedVolatility":{"raw":0.9367682104492188,"fmt":"93.68%"},"volume":{"raw":1,"fmt":"1","longFmt":"1"},"ask":{"raw":234.5,"fmt":"234.50"},"contractSymbol":"COIN270115C00090000","lastTradeDate":{"raw":1730912320,"fmt":"2024-11-06","longFmt":"2024-11-06T16:58"},"contractSize":"REGULAR","expiration":{"raw":1799971200,"fmt":"2027-01-15","longFmt":"2027-01-15T00:00"},"currency":"USD","bid":{"raw":230.5,"fmt":"230.50"},"lastPrice":{"raw":172.25,"fmt":"172.25"}},{"percentChange":{"raw":0.0,"fmt":"0.00%"},"openInterest":{"raw":1,"fmt":"1","longFmt":"1"},"change":{"raw":0.0,"fmt":"0.00"},"strike":{"raw":95.0,"fmt":"95.00"},"inTheMoney":true,"impliedVolatility":{"raw":0.9297187203979492,"fmt":"92.97%"},"ask":{"raw":231.5,"fmt":"231.50"},"contractSymbol":"COIN270115C00095000","lastTradeDate":{"raw":1730734271,"fmt":"2024-11-04","longFmt":"2024-11-04T15:31"},"contractSize":"REGULAR","expiration":{"raw":1799971200,"fmt":"2027-01-15","longFmt":"2027-01-15T00:00"},"currency":"USD","bid":{"raw":227.0,"fmt":"227.00"},"lastPrice":{"raw":112.7,"fmt":"112.70"}},{"percentChange":{"raw":0.0,"fmt":"0.00%"},"openInterest":{"raw":110,"fmt":"110","longFmt":"110"},"change":{"raw":0.0,"fmt":"0.00"},"strike":{"raw":100.0,"fmt":"100.00"},"inTheMoney":true,"impliedVolatility":{"raw":0.9177864666748048,"fmt":"91.78%"},"volume":{"raw":1,"fmt":"1","longFmt":"1"},"ask":{"raw":228.0,"fmt":"228.00"},"contractSymbol":"COIN270115C00100000","lastTradeDate":{"raw":1732205794,"fmt":"2024-11-21","longFmt":"2024-11-21T16:16"},"contractSize":"REGULAR","expiration":{"raw":1799971200,"fmt":"2027-01-15","longFmt":"2027-01-15T00:00"},"currency":"USD","bid":{"raw":223.5,"fmt":"223.50"},"lastPrice":{"raw":229.03,"fmt":"229.03"}},{"percentChange":{"raw":0.0,"fmt":"0.00%"},"openInterest":{"raw":8,"fmt":"8","longFmt":"8"},"change":{"raw":0.0,"fmt":"0.00"},"strike":{"raw":105.0,"fmt":"105.00"},"inTheMoney":true,"impliedVolatility":{"raw":0.9017343811035157,"fmt":"90.17%"},"volume":{"raw":3,"fmt":"3","longFmt":"3"},"ask":{"raw":224.0,"fmt":"224.00"},"contractSymbol":"COIN270115C00105000","lastTradeDate":{"raw":1732723582,"fmt":"2024-11-27","longFmt":"2024-11-27T16:06"},"contractSize":"REGULAR","expiration":{"raw":1799971200,"fmt":"2027-01-15","longFmt":"2027-01-15T00:00"},"currency":"USD","bid":{"raw":220.0,"fmt":"220.00"},"lastPrice":{"raw":219.25,"fmt":"219.25"}},{"percentChange":{"raw":0.0,"fmt":"0.00%"},"openInterest":{"raw":3,"fmt":"3","longFmt":"3"},"change":{"raw":0.0,"fmt":"0.00"},"strike":{"raw":110.0,"fmt":"110.00"},"inTheMoney":true,"impliedVolatility":{"raw":0.8979197219848631,"fmt":"89.79%"},"volume":{"raw":3,"fmt":"3","longFmt":"3"},"ask":{"raw":221.0,"fmt":"221.00"},"contractSymbol":"COIN270115C00110000","lastTradeDate":{"raw":1732118263,"fmt":"2024-11-20","longFmt":"2024-11-20T15:57"},"contractSize":"REGULAR","expiration":{"raw":1799971200,"fmt":"2027-01-15","longFmt":"2027-01-15T00:00"},"currency":"USD","bid":{"raw":217.0,"fmt":"217.00"},"lastPrice":{"raw":239.5,"fmt":"239.50"}},{"percentChange":{"raw":0.0,"fmt":"0.00%"},"openInterest":{"raw":3,"fmt":"3","longFmt":"3"},"change":{"raw":0.0,"fmt":"0.00"},"strike":{"raw":115.0,"fmt":"115.00"},"inTheMoney":true,"impliedVolatility":{"raw":0.8859264337158204,"fmt":"88.59%"},"volume":{"raw":3,"fmt":"3","longFmt":"3"},"ask":{"raw":217.5,"fmt":"217.50"},"contractSymbol":"COIN270115C00115000","lastTradeDate":{"raw":1732723541,"fmt":"2024-11-27","longFmt":"2024-11-27T16:05"},"contractSize":"REGULAR","expiration":{"raw":1799971200,"fmt":"2027-01-15","longFmt":"2027-01-15T00:00"},"currency":"USD","bid":{"raw":213.5,"fmt":"213.50"},"lastPrice":{"raw":213.0,"fmt":"213.00"}},{"percentChange":{"raw":0.0,"fmt":"0.00%"},"openInterest":{"raw":12,"fmt":"12","longFmt":"12"},"change":{"raw":0.0,"fmt":"0.00"},"strike":{"raw":120.0,"fmt":"120.00"},"inTheMoney":true,"impliedVolatility":{"raw":0.8848278118896484,"fmt":"88.48%"},"volume":{"raw":2,"fmt":"2","longFmt":"2"},"ask":{"raw":215.0,"fmt":"215.00"},"contractSymbol":"COIN270115C00120000","lastTradeDate":{"raw":1730991479,"fmt":"2024-11-07","longFmt":"2024-11-07T14:57"},"contractSize":"REGULAR","expiration":{"raw":1799971200,"fmt":"2027-01-15","longFmt":"2027-01-15T00:00"},"currency":"USD","bid":{"raw":210.5,"fmt":"210.50"},"lastPrice":{"raw":162.35,"fmt":"162.35"}},{"percentChange":{"raw":0.0,"fmt":"0.00%"},"openInterest":{"raw":1,"fmt":"1","longFmt":"1"},"change":{"raw":0.0,"fmt":"0.00"},"strike":{"raw":125.0,"fmt":"125.00"},"inTheMoney":true,"impliedVolatility":{"raw":0.8794872891235351,"fmt":"87.95%"},"volume":{"raw":1,"fmt":"1","longFmt":"1"},"ask":{"raw":212.0,"fmt":"212.00"},"contractSymbol":"COIN270115C00125000","lastTradeDate":{"raw":1731358277,"fmt":"2024-11-11","longFmt":"2024-11-11T20:51"},"contractSize":"REGULAR","expiration":{"raw":1799971200,"fmt":"2027-01-15","longFmt":"2027-01-15T00:00"},"currency":"USD","bid":{"raw":207.5,"fmt":"207.50"},"lastPrice":{"raw":233.15,"fmt":"233.15"}},{"percentChange":{"raw":0.0,"fmt":"0.00%"},"openInterest":{"raw":52,"fmt":"52","longFmt":"52"},"change":{"raw":0.0,"fmt":"0.00"},"strike":{"raw":130.0,"fmt":"130.00"},"inTheMoney":true,"impliedVolatility":{"raw":0.8737347831726072,"fmt":"87.37%"},"volume":{"raw":1,"fmt":"1","longFmt":"1"},"ask":{"raw":209.0,"fmt":"209.00"},"contractSymbol":"COIN270115C00130000","lastTradeDate":{"raw":1731691532,"fmt":"2024-11-15","longFmt":"2024-11-15T17:25"},"contractSize":"REGULAR","expiration":{"raw":1799971200,"fmt":"2027-01-15","longFmt":"2027-01-15T00:00"},"currency":"USD","bid":{"raw":204.5,"fmt":"204.50"},"lastPrice":{"raw":198.0,"fmt":"198.00"}},{"percentChange":{"raw":0.0,"fmt":"0.00%"},"openInterest":{"raw":5,"fmt":"5","longFmt":"5"},"change":{"raw":0.0,"fmt":"0.00"},"strike":{"raw":135.0,"fmt":"135.00"},"inTheMoney":true,"impliedVolatility":{"raw":0.8676465872192383,"fmt":"86.76%"},"volume":{"raw":1,"fmt":"1","longFmt":"1"},"ask":{"raw":206.0,"fmt":"206.00"},"contractSymbol":"COIN270115C00135000","lastTradeDate":{"raw":1732202985,"fmt":"2024-11-21","longFmt":"2024-11-21T15:29"},"contractSize":"REGULAR","expiration":{"raw":1799971200,"fmt":"2027-01-15","longFmt":"2027-01-15T00:00"},"currency":"USD","bid":{"raw":201.5,"fmt":"201.50"},"lastPrice":{"raw":197.21,"fmt":"197.21"}},{"percentChange":{"raw":0.0,"fmt":"0.00%"},"openInterest":{"raw":8,"fmt":"8","longFmt":"8"},"change":{"raw":0.0,"fmt":"0.00"},"strike":{"raw":140.0,"fmt":"140.00"},"inTheMoney":true,"impliedVolatility":{"raw":0.8612989944458008,"fmt":"86.13%"},"volume":{"raw":8,"fmt":"8","longFmt":"8"},"ask":{"raw":203.0,"fmt":"203.00"},"contractSymbol":"COIN270115C00140000","lastTradeDate":{"raw":1732130028,"fmt":"2024-11-20","longFmt":"2024-11-20T19:13"},"contractSize":"REGULAR","expiration":{"raw":1799971200,"fmt":"2027-01-15","longFmt":"2027-01-15T00:00"},"currency":"USD","bid":{"raw":198.5,"fmt":"198.50"},"lastPrice":{"raw":215.25,"fmt":"215.25"}},{"percentChange":{"raw":0.0,"fmt":"0.00%"},"openInterest":{"raw":80,"fmt":"80","longFmt":"80"},"change":{"raw":0.0,"fmt":"0.00"},"strike":{"raw":145.0,"fmt":"145.00"},"inTheMoney":true,"impliedVolatility":{"raw":0.854692004852295,"fmt":"85.47%"},"volume":{"raw":3,"fmt":"3","longFmt":"3"},"ask":{"raw":200.0,"fmt":"200.00"},"contractSymbol":"COIN270115C00145000","lastTradeDate":{"raw":1730836761,"fmt":"2024-11-05","longFmt":"2024-11-05T19:59"},"contractSize":"REGULAR","expiration":{"raw":1799971200,"fmt":"2027-01-15","longFmt":"2027-01-15T00:00"},"currency":"USD","bid":{"raw":195.5,"fmt":"195.50"},"lastPrice":{"raw":102.7,"fmt":"102.70"}},{"percentChange":{"raw":0.0,"fmt":"0.00%"},"openInterest":{"raw":88,"fmt":"88","longFmt":"88"},"change":{"raw":0.0,"fmt":"0.00"},"strike":{"raw":150.0,"fmt":"150.00"},"inTheMoney":true,"impliedVolatility":{"raw":0.8507552766418458,"fmt":"85.08%"},"volume":{"raw":1,"fmt":"1","longFmt":"1"},"ask":{"raw":197.0,"fmt":"197.00"},"contractSymbol":"COIN270115C00150000","lastTradeDate":{"raw":1732216633,"fmt":"2024-11-21","longFmt":"2024-11-21T19:17"},"contractSize":"REGULAR","expiration":{"raw":1799971200,"fmt":"2027-01-15","longFmt":"2027-01-15T00:00"},"currency":"USD","bid":{"raw":193.0,"fmt":"193.00"},"lastPrice":{"raw":203.14,"fmt":"203.14"}},{"percentChange":{"raw":0.0,"fmt":"0.00%"},"openInterest":{"raw":13,"fmt":"13","longFmt":"13"},"change":{"raw":0.0,"fmt":"0.00"},"strike":{"raw":155.0,"fmt":"155.00"},"inTheMoney":true,"impliedVolatility":{"raw":0.8436905279541016,"fmt":"84.37%"},"volume":{"raw":1,"fmt":"1","longFmt":"1"},"ask":{"raw":194.0,"fmt":"194.00"},"contractSymbol":"COIN270115C00155000","lastTradeDate":{"raw":1732308248,"fmt":"2024-11-22","longFmt":"2024-11-22T20:44"},"contractSize":"REGULAR","expiration":{"raw":1799971200,"fmt":"2027-01-15","longFmt":"2027-01-15T00:00"},"currency":"USD","bid":{"raw":190.0,"fmt":"190.00"},"lastPrice":{"raw":197.95,"fmt":"197.95"}},{"percentChange":{"raw":0.0,"fmt":"0.00%"},"openInterest":{"raw":9,"fmt":"9","longFmt":"9"},"change":{"raw":0.0,"fmt":"0.00"},"strike":{"raw":160.0,"fmt":"160.00"},"inTheMoney":true,"impliedVolatility":{"raw":0.8418900088500977,"fmt":"84.19%"},"volume":{"raw":1,"fmt":"1","longFmt":"1"},"ask":{"raw":191.5,"fmt":"191.50"},"contractSymbol":"COIN270115C00160000","lastTradeDate":{"raw":1732734018,"fmt":"2024-11-27","longFmt":"2024-11-27T19:00"},"contractSize":"REGULAR","expiration":{"raw":1799971200,"fmt":"2027-01-15","longFmt":"2027-01-15T00:00"},"currency":"USD","bid":{"raw":187.5,"fmt":"187.50"},"lastPrice":{"raw":194.0,"fmt":"194.00"}},{"percentChange":{"raw":0.0,"fmt":"0.00%"},"openInterest":{"raw":14,"fmt":"14","longFmt":"14"},"change":{"raw":0.0,"fmt":"0.00"},"strike":{"raw":165.0,"fmt":"165.00"},"inTheMoney":true,"impliedVolatility":{"raw":0.8370072451782226,"fmt":"83.70%"},"volume":{"raw":3,"fmt":"3","longFmt":"3"},"ask":{"raw":189.0,"fmt":"189.00"},"contractSymbol":"COIN270115C00165000","lastTradeDate":{"raw":1731003915,"fmt":"2024-11-07","longFmt":"2024-11-07T18:25"},"contractSize":"REGULAR","expiration":{"raw":1799971200,"fmt":"2027-01-15","longFmt":"2027-01-15T00:00"},"currency":"USD","bid":{"raw":184.5,"fmt":"184.50"},"lastPrice":{"raw":145.72,"fmt":"145.72"}},{"percentChange":{"raw":0.0,"fmt":"0.00%"},"openInterest":{"raw":23,"fmt":"23","longFmt":"23"},"change":{"raw":0.0,"fmt":"0.00"},"strike":{"raw":170.0,"fmt":"170.00"},"inTheMoney":true,"impliedVolatility":{"raw":0.8344743115234373,"fmt":"83.45%"},"volume":{"raw":11,"fmt":"11","longFmt":"11"},"ask":{"raw":186.5,"fmt":"186.50"},"contractSymbol":"COIN270115C00170000","lastTradeDate":{"raw":1731092494,"fmt":"2024-11-08","longFmt":"2024-11-08T19:01"},"contractSize":"REGULAR","expiration":{"raw":1799971200,"fmt":"2027-01-15","longFmt":"2027-01-15T00:00"},"currency":"USD","bid":{"raw":182.0,"fmt":"182.00"},"lastPrice":{"raw":155.73,"fmt":"155.73"}},{"percentChange":{"raw":0.0,"fmt":"0.00%"},"openInterest":{"raw":18,"fmt":"18","longFmt":"18"},"change":{"raw":0.0,"fmt":"0.00"},"strike":{"raw":175.0,"fmt":"175.00"},"inTheMoney":true,"impliedVolatility":{"raw":0.8290880128479003,"fmt":"82.91%"},"volume":{"raw":2,"fmt":"2","longFmt":"2"},"ask":{"raw":183.5,"fmt":"183.50"},"contractSymbol":"COIN270115C00175000","lastTradeDate":{"raw":1732736652,"fmt":"2024-11-27","longFmt":"2024-11-27T19:44"},"contractSize":"REGULAR","expiration":{"raw":1799971200,"fmt":"2027-01-15","longFmt":"2027-01-15T00:00"},"currency":"USD","bid":{"raw":179.5,"fmt":"179.50"},"lastPrice":{"raw":190.02,"fmt":"190.02"}},{"percentChange":{"raw":0.0,"fmt":"0.00%"},"openInterest":{"raw":65,"fmt":"65","longFmt":"65"},"change":{"raw":0.0,"fmt":"0.00"},"strike":{"raw":180.0,"fmt":"180.00"},"inTheMoney":true,"impliedVolatility":{"raw":0.8259447337341306,"fmt":"82.59%"},"volume":{"raw":1,"fmt":"1","longFmt":"1"},"ask":{"raw":181.0,"fmt":"181.00"},"contractSymbol":"COIN270115C00180000","lastTradeDate":{"raw":1732199847,"fmt":"2024-11-21","longFmt":"2024-11-21T14:37"},"contractSize":"REGULAR","expiration":{"raw":1799971200,"fmt":"2027-01-15","longFmt":"2027-01-15T00:00"},"currency":"USD","bid":{"raw":177.0,"fmt":"177.00"},"lastPrice":{"raw":191.84,"fmt":"191.84"}},{"percentChange":{"raw":13.629968,"fmt":"13.63%"},"openInterest":{"raw":17,"fmt":"17","longFmt":"17"},"change":{"raw":21.290009,"fmt":"21.29"},"strike":{"raw":185.0,"fmt":"185.00"},"inTheMoney":true,"impliedVolatility":{"raw":0.8248918878173828,"fmt":"82.49%"},"volume":{"raw":1,"fmt":"1","longFmt":"1"},"ask":{"raw":179.0,"fmt":"179.00"},"contractSymbol":"COIN270115C00185000","lastTradeDate":{"raw":1733169814,"fmt":"2024-12-02","longFmt":"2024-12-02T20:03"},"contractSize":"REGULAR","expiration":{"raw":1799971200,"fmt":"2027-01-15","longFmt":"2027-01-15T00:00"},"currency":"USD","bid":{"raw":174.5,"fmt":"174.50"},"lastPrice":{"raw":177.49,"fmt":"177.49"}},{"percentChange":{"raw":0.0,"fmt":"0.00%"},"openInterest":{"raw":11,"fmt":"11","longFmt":"11"},"change":{"raw":0.0,"fmt":"0.00"},"strike":{"raw":190.0,"fmt":"190.00"},"inTheMoney":true,"impliedVolatility":{"raw":0.823472834625244,"fmt":"82.35%"},"volume":{"raw":1,"fmt":"1","longFmt":"1"},"ask":{"raw":176.5,"fmt":"176.50"},"contractSymbol":"COIN270115C00190000","lastTradeDate":{"raw":1731597885,"fmt":"2024-11-14","longFmt":"2024-11-14T15:24"},"contractSize":"REGULAR","expiration":{"raw":1799971200,"fmt":"2027-01-15","longFmt":"2027-01-15T00:00"},"currency":"USD","bid":{"raw":172.5,"fmt":"172.50"},"lastPrice":{"raw":159.06,"fmt":"159.06"}},{"percentChange":{"raw":0.0,"fmt":"0.00%"},"openInterest":{"raw":28,"fmt":"28","longFmt":"28"},"change":{"raw":0.0,"fmt":"0.00"},"strike":{"raw":195.0,"fmt":"195.00"},"inTheMoney":true,"impliedVolatility":{"raw":0.8217180914306641,"fmt":"82.17%"},"volume":{"raw":1,"fmt":"1","longFmt":"1"},"ask":{"raw":174.5,"fmt":"174.50"},"contractSymbol":"COIN270115C00195000","lastTradeDate":{"raw":1731335877,"fmt":"2024-11-11","longFmt":"2024-11-11T14:37"},"contractSize":"REGULAR","expiration":{"raw":1799971200,"fmt":"2027-01-15","longFmt":"2027-01-15T00:00"},"currency":"USD","bid":{"raw":170.0,"fmt":"170.00"},"lastPrice":{"raw":178.97,"fmt":"178.97"}},{"percentChange":{"raw":0.0,"fmt":"0.00%"},"openInterest":{"raw":65,"fmt":"65","longFmt":"65"},"change":{"raw":0.0,"fmt":"0.00"},"strike":{"raw":200.0,"fmt":"200.00"},"inTheMoney":true,"impliedVolatility":{"raw":0.8174609318542478,"fmt":"81.75%"},"volume":{"raw":2,"fmt":"2","longFmt":"2"},"ask":{"raw":172.0,"fmt":"172.00"},"contractSymbol":"COIN270115C00200000","lastTradeDate":{"raw":1732893712,"fmt":"2024-11-29","longFmt":"2024-11-29T15:21"},"contractSize":"REGULAR","expiration":{"raw":1799971200,"fmt":"2027-01-15","longFmt":"2027-01-15T00:00"},"currency":"USD","bid":{"raw":167.5,"fmt":"167.50"},"lastPrice":{"raw":179.7,"fmt":"179.70"}},{"percentChange":{"raw":0.0,"fmt":"0.00%"},"openInterest":{"raw":18,"fmt":"18","longFmt":"18"},"change":{"raw":0.0,"fmt":"0.00"},"strike":{"raw":210.0,"fmt":"210.00"},"inTheMoney":true,"impliedVolatility":{"raw":0.8148059291076661,"fmt":"81.48%"},"volume":{"raw":1,"fmt":"1","longFmt":"1"},"ask":{"raw":167.5,"fmt":"167.50"},"contractSymbol":"COIN270115C00210000","lastTradeDate":{"raw":1732200861,"fmt":"2024-11-21","longFmt":"2024-11-21T14:54"},"contractSize":"REGULAR","expiration":{"raw":1799971200,"fmt":"2027-01-15","longFmt":"2027-01-15T00:00"},"currency":"USD","bid":{"raw":163.5,"fmt":"163.50"},"lastPrice":{"raw":175.15,"fmt":"175.15"}},{"percentChange":{"raw":3.0686698,"fmt":"3.07%"},"openInterest":{"raw":27,"fmt":"27","longFmt":"27"},"change":{"raw":4.919998,"fmt":"4.92"},"strike":{"raw":220.0,"fmt":"220.00"},"inTheMoney":true,"impliedVolatility":{"raw":0.8110828218078612,"fmt":"81.11%"},"volume":{"raw":2,"fmt":"2","longFmt":"2"},"ask":{"raw":163.5,"fmt":"163.50"},"contractSymbol":"COIN270115C00220000","lastTradeDate":{"raw":1733153542,"fmt":"2024-12-02","longFmt":"2024-12-02T15:32"},"contractSize":"REGULAR","expiration":{"raw":1799971200,"fmt":"2027-01-15","longFmt":"2027-01-15T00:00"},"currency":"USD","bid":{"raw":159.0,"fmt":"159.00"},"lastPrice":{"raw":165.25,"fmt":"165.25"}},{"percentChange":{"raw":4.3862495,"fmt":"4.39%"},"openInterest":{"raw":29,"fmt":"29","longFmt":"29"},"change":{"raw":6.850006,"fmt":"6.85"},"strike":{"raw":230.0,"fmt":"230.00"},"inTheMoney":true,"impliedVolatility":{"raw":0.8064289376831054,"fmt":"80.64%"},"volume":{"raw":4,"fmt":"4","longFmt":"4"},"ask":{"raw":159.0,"fmt":"159.00"},"contractSymbol":"COIN270115C00230000","lastTradeDate":{"raw":1733158300,"fmt":"2024-12-02","longFmt":"2024-12-02T16:51"},"contractSize":"REGULAR","expiration":{"raw":1799971200,"fmt":"2027-01-15","longFmt":"2027-01-15T00:00"},"currency":"USD","bid":{"raw":155.0,"fmt":"155.00"},"lastPrice":{"raw":163.02,"fmt":"163.02"}},{"percentChange":{"raw":-1.6796248,"fmt":"-1.68%"},"openInterest":{"raw":21,"fmt":"21","longFmt":"21"},"change":{"raw":-2.699997,"fmt":"-2.70"},"strike":{"raw":240.0,"fmt":"240.00"},"inTheMoney":true,"impliedVolatility":{"raw":0.8048420394897461,"fmt":"80.48%"},"volume":{"raw":2,"fmt":"2","longFmt":"2"},"ask":{"raw":155.5,"fmt":"155.50"},"contractSymbol":"COIN270115C00240000","lastTradeDate":{"raw":1733153312,"fmt":"2024-12-02","longFmt":"2024-12-02T15:28"},"contractSize":"REGULAR","expiration":{"raw":1799971200,"fmt":"2027-01-15","longFmt":"2027-01-15T00:00"},"currency":"USD","bid":{"raw":151.0,"fmt":"151.00"},"lastPrice":{"raw":158.05,"fmt":"158.05"}},{"percentChange":{"raw":0.0,"fmt":"0.00%"},"openInterest":{"raw":92,"fmt":"92","longFmt":"92"},"change":{"raw":0.0,"fmt":"0.00"},"strike":{"raw":250.0,"fmt":"250.00"},"inTheMoney":true,"impliedVolatility":{"raw":0.8004933280944824,"fmt":"80.05%"},"volume":{"raw":1,"fmt":"1","longFmt":"1"},"ask":{"raw":151.5,"fmt":"151.50"},"contractSymbol":"COIN270115C00250000","lastTradeDate":{"raw":1732902722,"fmt":"2024-11-29","longFmt":"2024-11-29T17:52"},"contractSize":"REGULAR","expiration":{"raw":1799971200,"fmt":"2027-01-15","longFmt":"2027-01-15T00:00"},"currency":"USD","bid":{"raw":147.0,"fmt":"147.00"},"lastPrice":{"raw":147.32,"fmt":"147.32"}},{"percentChange":{"raw":0.0,"fmt":"0.00%"},"openInterest":{"raw":43,"fmt":"43","longFmt":"43"},"change":{"raw":0.0,"fmt":"0.00"},"strike":{"raw":260.0,"fmt":"260.00"},"inTheMoney":true,"impliedVolatility":{"raw":0.7991047921752931,"fmt":"79.91%"},"volume":{"raw":1,"fmt":"1","longFmt":"1"},"ask":{"raw":148.0,"fmt":"148.00"},"contractSymbol":"COIN270115C00260000","lastTradeDate":{"raw":1732721834,"fmt":"2024-11-27","longFmt":"2024-11-27T15:37"},"contractSize":"REGULAR","expiration":{"raw":1799971200,"fmt":"2027-01-15","longFmt":"2027-01-15T00:00"},"currency":"USD","bid":{"raw":143.5,"fmt":"143.50"},"lastPrice":{"raw":152.0,"fmt":"152.00"}},{"percentChange":{"raw":-12.902635,"fmt":"-12.90%"},"openInterest":{"raw":27,"fmt":"27","longFmt":"27"},"change":{"raw":-21.11,"fmt":"-21.11"},"strike":{"raw":270.0,"fmt":"270.00"},"inTheMoney":true,"impliedVolatility":{"raw":0.7951375466918945,"fmt":"79.51%"},"volume":{"raw":1,"fmt":"1","longFmt":"1"},"ask":{"raw":144.0,"fmt":"144.00"},"contractSymbol":"COIN270115C00270000","lastTradeDate":{"raw":1733162230,"fmt":"2024-12-02","longFmt":"2024-12-02T17:57"},"contractSize":"REGULAR","expiration":{"raw":1799971200,"fmt":"2027-01-15","longFmt":"2027-01-15T00:00"},"currency":"USD","bid":{"raw":140.0,"fmt":"140.00"},"lastPrice":{"raw":142.5,"fmt":"142.50"}},{"percentChange":{"raw":0.0,"fmt":"0.00%"},"openInterest":{"raw":18,"fmt":"18","longFmt":"18"},"change":{"raw":0.0,"fmt":"0.00"},"strike":{"raw":280.0,"fmt":"280.00"},"inTheMoney":true,"impliedVolatility":{"raw":0.7922994403076171,"fmt":"79.23%"},"volume":{"raw":3,"fmt":"3","longFmt":"3"},"ask":{"raw":140.5,"fmt":"140.50"},"contractSymbol":"COIN270115C00280000","lastTradeDate":{"raw":1732892875,"fmt":"2024-11-29","longFmt":"2024-11-29T15:07"},"contractSize":"REGULAR","expiration":{"raw":1799971200,"fmt":"2027-01-15","longFmt":"2027-01-15T00:00"},"currency":"USD","bid":{"raw":136.5,"fmt":"136.50"},"lastPrice":{"raw":149.5,"fmt":"149.50"}},{"percentChange":{"raw":0.0,"fmt":"0.00%"},"openInterest":{"raw":21,"fmt":"21","longFmt":"21"},"change":{"raw":0.0,"fmt":"0.00"},"strike":{"raw":290.0,"fmt":"290.00"},"inTheMoney":true,"impliedVolatility":{"raw":0.792268923034668,"fmt":"79.23%"},"volume":{"raw":2,"fmt":"2","longFmt":"2"},"ask":{"raw":137.5,"fmt":"137.50"},"contractSymbol":"COIN270115C00290000","lastTradeDate":{"raw":1732652468,"fmt":"2024-11-26","longFmt":"2024-11-26T20:21"},"contractSize":"REGULAR","expiration":{"raw":1799971200,"fmt":"2027-01-15","longFmt":"2027-01-15T00:00"},"currency":"USD","bid":{"raw":133.5,"fmt":"133.50"},"lastPrice":{"raw":129.79,"fmt":"129.79"}},{"percentChange":{"raw":1.1690629,"fmt":"1.17%"},"openInterest":{"raw":168,"fmt":"168","longFmt":"168"},"change":{"raw":1.5599976,"fmt":"1.56"},"strike":{"raw":300.0,"fmt":"300.00"},"inTheMoney":true,"impliedVolatility":{"raw":0.788164349822998,"fmt":"78.82%"},"volume":{"raw":5,"fmt":"5","longFmt":"5"},"ask":{"raw":134.0,"fmt":"134.00"},"contractSymbol":"COIN270115C00300000","lastTradeDate":{"raw":1733171511,"fmt":"2024-12-02","longFmt":"2024-12-02T20:31"},"contractSize":"REGULAR","expiration":{"raw":1799971200,"fmt":"2027-01-15","longFmt":"2027-01-15T00:00"},"currency":"USD","bid":{"raw":130.0,"fmt":"130.00"},"lastPrice":{"raw":135.0,"fmt":"135.00"}},{"percentChange":{"raw":-1.2168208,"fmt":"-1.22%"},"openInterest":{"raw":25,"fmt":"25","longFmt":"25"},"change":{"raw":-1.6500092,"fmt":"-1.65"},"strike":{"raw":310.0,"fmt":"310.00"},"inTheMoney":false,"impliedVolatility":{"raw":0.7956563403320311,"fmt":"79.57%"},"volume":{"raw":2,"fmt":"2","longFmt":"2"},"ask":{"raw":131.65,"fmt":"131.65"},"contractSymbol":"COIN270115C00310000","lastTradeDate":{"raw":1733156856,"fmt":"2024-12-02","longFmt":"2024-12-02T16:27"},"contractSize":"REGULAR","expiration":{"raw":1799971200,"fmt":"2027-01-15","longFmt":"2027-01-15T00:00"},"currency":"USD","bid":{"raw":129.0,"fmt":"129.00"},"lastPrice":{"raw":133.95,"fmt":"133.95"}},{"percentChange":{"raw":-4.142577,"fmt":"-4.14%"},"openInterest":{"raw":40,"fmt":"40","longFmt":"40"},"change":{"raw":-5.6600037,"fmt":"-5.66"},"strike":{"raw":320.0,"fmt":"320.00"},"inTheMoney":false,"impliedVolatility":{"raw":0.7866232275390624,"fmt":"78.66%"},"volume":{"raw":6,"fmt":"6","longFmt":"6"},"ask":{"raw":128.5,"fmt":"128.50"},"contractSymbol":"COIN270115C00320000","lastTradeDate":{"raw":1733155267,"fmt":"2024-12-02","longFmt":"2024-12-02T16:01"},"contractSize":"REGULAR","expiration":{"raw":1799971200,"fmt":"2027-01-15","longFmt":"2027-01-15T00:00"},"currency":"USD","bid":{"raw":124.0,"fmt":"124.00"},"lastPrice":{"raw":130.97,"fmt":"130.97"}},{"percentChange":{"raw":-4.629902,"fmt":"-4.63%"},"openInterest":{"raw":782,"fmt":"782","longFmt":"782"},"change":{"raw":-6.1799927,"fmt":"-6.18"},"strike":{"raw":330.0,"fmt":"330.00"},"inTheMoney":false,"impliedVolatility":{"raw":0.7858145198059083,"fmt":"78.58%"},"volume":{"raw":1,"fmt":"1","longFmt":"1"},"ask":{"raw":125.5,"fmt":"125.50"},"contractSymbol":"COIN270115C00330000","lastTradeDate":{"raw":1733153728,"fmt":"2024-12-02","longFmt":"2024-12-02T15:35"},"contractSize":"REGULAR","expiration":{"raw":1799971200,"fmt":"2027-01-15","longFmt":"2027-01-15T00:00"},"currency":"USD","bid":{"raw":121.5,"fmt":"121.50"},"lastPrice":{"raw":127.3,"fmt":"127.30"}},{"percentChange":{"raw":-4.0069547,"fmt":"-4.01%"},"openInterest":{"raw":11,"fmt":"11","longFmt":"11"},"change":{"raw":-5.0699997,"fmt":"-5.07"},"strike":{"raw":340.0,"fmt":"340.00"},"inTheMoney":false,"impliedVolatility":{"raw":0.7829001202392578,"fmt":"78.29%"},"volume":{"raw":2,"fmt":"2","longFmt":"2"},"ask":{"raw":122.5,"fmt":"122.50"},"contractSymbol":"COIN270115C00340000","lastTradeDate":{"raw":1733168748,"fmt":"2024-12-02","longFmt":"2024-12-02T19:45"},"contractSize":"REGULAR","expiration":{"raw":1799971200,"fmt":"2027-01-15","longFmt":"2027-01-15T00:00"},"currency":"USD","bid":{"raw":118.5,"fmt":"118.50"},"lastPrice":{"raw":121.46,"fmt":"121.46"}},{"percentChange":{"raw":-2.0325203,"fmt":"-2.03%"},"openInterest":{"raw":204,"fmt":"204","longFmt":"204"},"change":{"raw":-2.5,"fmt":"-2.50"},"strike":{"raw":350.0,"fmt":"350.00"},"inTheMoney":false,"impliedVolatility":{"raw":0.7826712406921388,"fmt":"78.27%"},"volume":{"raw":2,"fmt":"2","longFmt":"2"},"ask":{"raw":120.0,"fmt":"120.00"},"contractSymbol":"COIN270115C00350000","lastTradeDate":{"raw":1733165453,"fmt":"2024-12-02","longFmt":"2024-12-02T18:50"},"contractSize":"REGULAR","expiration":{"raw":1799971200,"fmt":"2027-01-15","longFmt":"2027-01-15T00:00"},"currency":"USD","bid":{"raw":116.0,"fmt":"116.00"},"lastPrice":{"raw":120.5,"fmt":"120.50"}},{"percentChange":{"raw":0.0,"fmt":"0.00%"},"openInterest":{"raw":39,"fmt":"39","longFmt":"39"},"change":{"raw":0.0,"fmt":"0.00"},"strike":{"raw":360.0,"fmt":"360.00"},"inTheMoney":false,"impliedVolatility":{"raw":0.7780936497497559,"fmt":"77.81%"},"volume":{"raw":2,"fmt":"2","longFmt":"2"},"ask":{"raw":116.75,"fmt":"116.75"},"contractSymbol":"COIN270115C00360000","lastTradeDate":{"raw":1732561883,"fmt":"2024-11-25","longFmt":"2024-11-25T19:11"},"contractSize":"REGULAR","expiration":{"raw":1799971200,"fmt":"2027-01-15","longFmt":"2027-01-15T00:00"},"currency":"USD","bid":{"raw":113.0,"fmt":"113.00"},"lastPrice":{"raw":125.0,"fmt":"125.00"}},{"percentChange":{"raw":0.0,"fmt":"0.00%"},"openInterest":{"raw":10,"fmt":"10","longFmt":"10"},"change":{"raw":0.0,"fmt":"0.00"},"strike":{"raw":370.0,"fmt":"370.00"},"inTheMoney":false,"impliedVolatility":{"raw":0.7768271829223633,"fmt":"77.68%"},"volume":{"raw":1,"fmt":"1","longFmt":"1"},"ask":{"raw":114.2,"fmt":"114.20"},"contractSymbol":"COIN270115C00370000","lastTradeDate":{"raw":1732646855,"fmt":"2024-11-26","longFmt":"2024-11-26T18:47"},"contractSize":"REGULAR","expiration":{"raw":1799971200,"fmt":"2027-01-15","longFmt":"2027-01-15T00:00"},"currency":"USD","bid":{"raw":110.5,"fmt":"110.50"},"lastPrice":{"raw":112.94,"fmt":"112.94"}},{"percentChange":{"raw":0.0,"fmt":"0.00%"},"openInterest":{"raw":47,"fmt":"47","longFmt":"47"},"change":{"raw":0.0,"fmt":"0.00"},"strike":{"raw":380.0,"fmt":"380.00"},"inTheMoney":false,"impliedVolatility":{"raw":0.7777274424743652,"fmt":"77.77%"},"volume":{"raw":1,"fmt":"1","longFmt":"1"},"ask":{"raw":112.5,"fmt":"112.50"},"contractSymbol":"COIN270115C00380000","lastTradeDate":{"raw":1732549811,"fmt":"2024-11-25","longFmt":"2024-11-25T15:50"},"contractSize":"REGULAR","expiration":{"raw":1799971200,"fmt":"2027-01-15","longFmt":"2027-01-15T00:00"},"currency":"USD","bid":{"raw":108.0,"fmt":"108.00"},"lastPrice":{"raw":122.08,"fmt":"122.08"}},{"percentChange":{"raw":0.0,"fmt":"0.00%"},"openInterest":{"raw":7,"fmt":"7","longFmt":"7"},"change":{"raw":0.0,"fmt":"0.00"},"strike":{"raw":390.0,"fmt":"390.00"},"inTheMoney":false,"impliedVolatility":{"raw":0.7757819663238528,"fmt":"77.58%"},"volume":{"raw":2,"fmt":"2","longFmt":"2"},"ask":{"raw":110.0,"fmt":"110.00"},"contractSymbol":"COIN270115C00390000","lastTradeDate":{"raw":1732568242,"fmt":"2024-11-25","longFmt":"2024-11-25T20:57"},"contractSize":"REGULAR","expiration":{"raw":1799971200,"fmt":"2027-01-15","longFmt":"2027-01-15T00:00"},"currency":"USD","bid":{"raw":105.5,"fmt":"105.50"},"lastPrice":{"raw":118.6,"fmt":"118.60"}},{"percentChange":{"raw":-0.48090723,"fmt":"-0.48%"},"openInterest":{"raw":122,"fmt":"122","longFmt":"122"},"change":{"raw":-0.51000214,"fmt":"-0.51"},"strike":{"raw":400.0,"fmt":"400.00"},"inTheMoney":false,"impliedVolatility":{"raw":0.7749656292724609,"fmt":"77.50%"},"volume":{"raw":4,"fmt":"4","longFmt":"4"},"ask":{"raw":107.5,"fmt":"107.50"},"contractSymbol":"COIN270115C00400000","lastTradeDate":{"raw":1733165453,"fmt":"2024-12-02","longFmt":"2024-12-02T18:50"},"contractSize":"REGULAR","expiration":{"raw":1799971200,"fmt":"2027-01-15","longFmt":"2027-01-15T00:00"},"currency":"USD","bid":{"raw":103.5,"fmt":"103.50"},"lastPrice":{"raw":105.54,"fmt":"105.54"}},{"percentChange":{"raw":0.0,"fmt":"0.00%"},"openInterest":{"raw":27,"fmt":"27","longFmt":"27"},"change":{"raw":0.0,"fmt":"0.00"},"strike":{"raw":410.0,"fmt":"410.00"},"inTheMoney":false,"impliedVolatility":{"raw":0.7737907142639162,"fmt":"77.38%"},"volume":{"raw":15,"fmt":"15","longFmt":"15"},"ask":{"raw":105.5,"fmt":"105.50"},"contractSymbol":"COIN270115C00410000","lastTradeDate":{"raw":1732285820,"fmt":"2024-11-22","longFmt":"2024-11-22T14:30"},"contractSize":"REGULAR","expiration":{"raw":1799971200,"fmt":"2027-01-15","longFmt":"2027-01-15T00:00"},"currency":"USD","bid":{"raw":101.0,"fmt":"101.00"},"lastPrice":{"raw":104.1,"fmt":"104.10"}},{"percentChange":{"raw":0.0,"fmt":"0.00%"},"openInterest":{"raw":12,"fmt":"12","longFmt":"12"},"change":{"raw":0.0,"fmt":"0.00"},"strike":{"raw":420.0,"fmt":"420.00"},"inTheMoney":false,"impliedVolatility":{"raw":0.7722724799346924,"fmt":"77.23%"},"volume":{"raw":10,"fmt":"10","longFmt":"10"},"ask":{"raw":103.0,"fmt":"103.00"},"contractSymbol":"COIN270115C00420000","lastTradeDate":{"raw":1732899563,"fmt":"2024-11-29","longFmt":"2024-11-29T16:59"},"contractSize":"REGULAR","expiration":{"raw":1799971200,"fmt":"2027-01-15","longFmt":"2027-01-15T00:00"},"currency":"USD","bid":{"raw":99.0,"fmt":"99.00"},"lastPrice":{"raw":103.88,"fmt":"103.88"}},{"percentChange":{"raw":0.0,"fmt":"0.00%"},"openInterest":{"raw":51,"fmt":"51","longFmt":"51"},"change":{"raw":0.0,"fmt":"0.00"},"strike":{"raw":430.0,"fmt":"430.00"},"inTheMoney":false,"impliedVolatility":{"raw":0.7704261849212646,"fmt":"77.04%"},"volume":{"raw":1,"fmt":"1","longFmt":"1"},"ask":{"raw":101.0,"fmt":"101.00"},"contractSymbol":"COIN270115C00430000","lastTradeDate":{"raw":1732900394,"fmt":"2024-11-29","longFmt":"2024-11-29T17:13"},"contractSize":"REGULAR","expiration":{"raw":1799971200,"fmt":"2027-01-15","longFmt":"2027-01-15T00:00"},"currency":"USD","bid":{"raw":96.5,"fmt":"96.50"},"lastPrice":{"raw":99.0,"fmt":"99.00"}},{"percentChange":{"raw":-3.3486285,"fmt":"-3.35%"},"openInterest":{"raw":5,"fmt":"5","longFmt":"5"},"change":{"raw":-3.4300003,"fmt":"-3.43"},"strike":{"raw":440.0,"fmt":"440.00"},"inTheMoney":false,"impliedVolatility":{"raw":0.7697319169616699,"fmt":"76.97%"},"volume":{"raw":2,"fmt":"2","longFmt":"2"},"ask":{"raw":99.0,"fmt":"99.00"},"contractSymbol":"COIN270115C00440000","lastTradeDate":{"raw":1733160511,"fmt":"2024-12-02","longFmt":"2024-12-02T17:28"},"contractSize":"REGULAR","expiration":{"raw":1799971200,"fmt":"2027-01-15","longFmt":"2027-01-15T00:00"},"currency":"USD","bid":{"raw":94.5,"fmt":"94.50"},"lastPrice":{"raw":99.0,"fmt":"99.00"}},{"percentChange":{"raw":0.0,"fmt":"0.00%"},"openInterest":{"raw":511,"fmt":"511","longFmt":"511"},"change":{"raw":0.0,"fmt":"0.00"},"strike":{"raw":450.0,"fmt":"450.00"},"inTheMoney":false,"impliedVolatility":{"raw":0.768724846954346,"fmt":"76.87%"},"volume":{"raw":1,"fmt":"1","longFmt":"1"},"ask":{"raw":97.0,"fmt":"97.00"},"contractSymbol":"COIN270115C00450000","lastTradeDate":{"raw":1732124300,"fmt":"2024-11-20","longFmt":"2024-11-20T17:38"},"contractSize":"REGULAR","expiration":{"raw":1799971200,"fmt":"2027-01-15","longFmt":"2027-01-15T00:00"},"currency":"USD","bid":{"raw":92.5,"fmt":"92.50"},"lastPrice":{"raw":109.5,"fmt":"109.50"}},{"percentChange":{"raw":0.0,"fmt":"0.00%"},"openInterest":{"raw":12,"fmt":"12","longFmt":"12"},"change":{"raw":0.0,"fmt":"0.00"},"strike":{"raw":460.0,"fmt":"460.00"},"inTheMoney":false,"impliedVolatility":{"raw":0.7688698040008545,"fmt":"76.89%"},"volume":{"raw":1,"fmt":"1","longFmt":"1"},"ask":{"raw":95.5,"fmt":"95.50"},"contractSymbol":"COIN270115C00460000","lastTradeDate":{"raw":1731947213,"fmt":"2024-11-18","longFmt":"2024-11-18T16:26"},"contractSize":"REGULAR","expiration":{"raw":1799971200,"fmt":"2027-01-15","longFmt":"2027-01-15T00:00"},"currency":"USD","bid":{"raw":90.5,"fmt":"90.50"},"lastPrice":{"raw":102.5,"fmt":"102.50"}},{"percentChange":{"raw":0.0,"fmt":"0.00%"},"openInterest":{"raw":17,"fmt":"17","longFmt":"17"},"change":{"raw":0.0,"fmt":"0.00"},"strike":{"raw":470.0,"fmt":"470.00"},"inTheMoney":false,"impliedVolatility":{"raw":0.7672905351257324,"fmt":"76.73%"},"volume":{"raw":1,"fmt":"1","longFmt":"1"},"ask":{"raw":93.5,"fmt":"93.50"},"contractSymbol":"COIN270115C00470000","lastTradeDate":{"raw":1731941188,"fmt":"2024-11-18","longFmt":"2024-11-18T14:46"},"contractSize":"REGULAR","expiration":{"raw":1799971200,"fmt":"2027-01-15","longFmt":"2027-01-15T00:00"},"currency":"USD","bid":{"raw":88.5,"fmt":"88.50"},"lastPrice":{"raw":87.0,"fmt":"87.00"}},{"percentChange":{"raw":0.0,"fmt":"0.00%"},"openInterest":{"raw":13,"fmt":"13","longFmt":"13"},"change":{"raw":0.0,"fmt":"0.00"},"strike":{"raw":480.0,"fmt":"480.00"},"inTheMoney":false,"impliedVolatility":{"raw":0.7668709226226809,"fmt":"76.69%"},"volume":{"raw":5,"fmt":"5","longFmt":"5"},"ask":{"raw":91.5,"fmt":"91.50"},"contractSymbol":"COIN270115C00480000","lastTradeDate":{"raw":1732899563,"fmt":"2024-11-29","longFmt":"2024-11-29T16:59"},"contractSize":"REGULAR","expiration":{"raw":1799971200,"fmt":"2027-01-15","longFmt":"2027-01-15T00:00"},"currency":"USD","bid":{"raw":87.0,"fmt":"87.00"},"lastPrice":{"raw":91.93,"fmt":"91.93"}},{"percentChange":{"raw":0.0,"fmt":"0.00%"},"openInterest":{"raw":1,"fmt":"1","longFmt":"1"},"change":{"raw":0.0,"fmt":"0.00"},"strike":{"raw":490.0,"fmt":"490.00"},"inTheMoney":false,"impliedVolatility":{"raw":0.7647576014709474,"fmt":"76.48%"},"volume":{"raw":1,"fmt":"1","longFmt":"1"},"ask":{"raw":89.5,"fmt":"89.50"},"contractSymbol":"COIN270115C00490000","lastTradeDate":{"raw":1732120068,"fmt":"2024-11-20","longFmt":"2024-11-20T16:27"},"contractSize":"REGULAR","expiration":{"raw":1799971200,"fmt":"2027-01-15","longFmt":"2027-01-15T00:00"},"currency":"USD","bid":{"raw":85.0,"fmt":"85.00"},"lastPrice":{"raw":101.0,"fmt":"101.00"}},{"percentChange":{"raw":2.0527859,"fmt":"2.05%"},"openInterest":{"raw":1167,"fmt":"1,167","longFmt":"1,167"},"change":{"raw":1.75,"fmt":"1.75"},"strike":{"raw":500.0,"fmt":"500.00"},"inTheMoney":false,"impliedVolatility":{"raw":0.7652611364746094,"fmt":"76.53%"},"volume":{"raw":20,"fmt":"20","longFmt":"20"},"ask":{"raw":88.0,"fmt":"88.00"},"contractSymbol":"COIN270115C00500000","lastTradeDate":{"raw":1733167427,"fmt":"2024-12-02","longFmt":"2024-12-02T19:23"},"contractSize":"REGULAR","expiration":{"raw":1799971200,"fmt":"2027-01-15","longFmt":"2027-01-15T00:00"},"currency":"USD","bid":{"raw":83.5,"fmt":"83.50"},"lastPrice":{"raw":87.0,"fmt":"87.00"}},{"percentChange":{"raw":0.0,"fmt":"0.00%"},"openInterest":{"raw":19,"fmt":"19","longFmt":"19"},"change":{"raw":0.0,"fmt":"0.00"},"strike":{"raw":510.0,"fmt":"510.00"},"inTheMoney":false,"impliedVolatility":{"raw":0.7640938507843019,"fmt":"76.41%"},"volume":{"raw":10,"fmt":"10","longFmt":"10"},"ask":{"raw":86.0,"fmt":"86.00"},"contractSymbol":"COIN270115C00510000","lastTradeDate":{"raw":1732732487,"fmt":"2024-11-27","longFmt":"2024-11-27T18:34"},"contractSize":"REGULAR","expiration":{"raw":1799971200,"fmt":"2027-01-15","longFmt":"2027-01-15T00:00"},"currency":"USD","bid":{"raw":82.0,"fmt":"82.00"},"lastPrice":{"raw":87.82,"fmt":"87.82"}},{"percentChange":{"raw":0.0,"fmt":"0.00%"},"openInterest":{"raw":5,"fmt":"5","longFmt":"5"},"change":{"raw":0.0,"fmt":"0.00"},"strike":{"raw":520.0,"fmt":"520.00"},"inTheMoney":false,"impliedVolatility":{"raw":0.7641167387390138,"fmt":"76.41%"},"volume":{"raw":1,"fmt":"1","longFmt":"1"},"ask":{"raw":84.5,"fmt":"84.50"},"contractSymbol":"COIN270115C00520000","lastTradeDate":{"raw":1732653506,"fmt":"2024-11-26","longFmt":"2024-11-26T20:38"},"contractSize":"REGULAR","expiration":{"raw":1799971200,"fmt":"2027-01-15","longFmt":"2027-01-15T00:00"},"currency":"USD","bid":{"raw":80.5,"fmt":"80.50"},"lastPrice":{"raw":78.0,"fmt":"78.00"}},{"percentChange":{"raw":0.0,"fmt":"0.00%"},"openInterest":{"raw":6,"fmt":"6","longFmt":"6"},"change":{"raw":0.0,"fmt":"0.00"},"strike":{"raw":530.0,"fmt":"530.00"},"inTheMoney":false,"impliedVolatility":{"raw":0.7624840646362305,"fmt":"76.25%"},"volume":{"raw":1,"fmt":"1","longFmt":"1"},"ask":{"raw":83.0,"fmt":"83.00"},"contractSymbol":"COIN270115C00530000","lastTradeDate":{"raw":1731962184,"fmt":"2024-11-18","longFmt":"2024-11-18T20:36"},"contractSize":"REGULAR","expiration":{"raw":1799971200,"fmt":"2027-01-15","longFmt":"2027-01-15T00:00"},"currency":"USD","bid":{"raw":78.5,"fmt":"78.50"},"lastPrice":{"raw":100.0,"fmt":"100.00"}},{"percentChange":{"raw":0.0,"fmt":"0.00%"},"openInterest":{"raw":39,"fmt":"39","longFmt":"39"},"change":{"raw":0.0,"fmt":"0.00"},"strike":{"raw":540.0,"fmt":"540.00"},"inTheMoney":false,"impliedVolatility":{"raw":0.7634911346435547,"fmt":"76.35%"},"volume":{"raw":2,"fmt":"2","longFmt":"2"},"ask":{"raw":81.5,"fmt":"81.50"},"contractSymbol":"COIN270115C00540000","lastTradeDate":{"raw":1732900676,"fmt":"2024-11-29","longFmt":"2024-11-29T17:17"},"contractSize":"REGULAR","expiration":{"raw":1799971200,"fmt":"2027-01-15","longFmt":"2027-01-15T00:00"},"currency":"USD","bid":{"raw":77.5,"fmt":"77.50"},"lastPrice":{"raw":80.0,"fmt":"80.00"}},{"percentChange":{"raw":0.0,"fmt":"0.00%"},"openInterest":{"raw":293,"fmt":"293","longFmt":"293"},"change":{"raw":0.0,"fmt":"0.00"},"strike":{"raw":550.0,"fmt":"550.00"},"inTheMoney":false,"impliedVolatility":{"raw":0.7679695444488528,"fmt":"76.80%"},"volume":{"raw":2,"fmt":"2","longFmt":"2"},"ask":{"raw":80.0,"fmt":"80.00"},"contractSymbol":"COIN270115C00550000","lastTradeDate":{"raw":1732123227,"fmt":"2024-11-20","longFmt":"2024-11-20T17:20"},"contractSize":"REGULAR","expiration":{"raw":1799971200,"fmt":"2027-01-15","longFmt":"2027-01-15T00:00"},"currency":"USD","bid":{"raw":77.8,"fmt":"77.80"},"lastPrice":{"raw":86.68,"fmt":"86.68"}},{"percentChange":{"raw":0.0,"fmt":"0.00%"},"openInterest":{"raw":2,"fmt":"2","longFmt":"2"},"change":{"raw":0.0,"fmt":"0.00"},"strike":{"raw":570.0,"fmt":"570.00"},"inTheMoney":false,"impliedVolatility":{"raw":0.7646660496520996,"fmt":"76.47%"},"volume":{"raw":1,"fmt":"1","longFmt":"1"},"ask":{"raw":77.0,"fmt":"77.00"},"contractSymbol":"COIN270115C00570000","lastTradeDate":{"raw":1732549492,"fmt":"2024-11-25","longFmt":"2024-11-25T15:44"},"contractSize":"REGULAR","expiration":{"raw":1799971200,"fmt":"2027-01-15","longFmt":"2027-01-15T00:00"},"currency":"USD","bid":{"raw":74.3,"fmt":"74.30"},"lastPrice":{"raw":83.8,"fmt":"83.80"}},{"percentChange":{"raw":14.241577,"fmt":"14.24%"},"openInterest":{"raw":1,"fmt":"1","longFmt":"1"},"change":{"raw":9.68,"fmt":"9.68"},"strike":{"raw":580.0,"fmt":"580.00"},"inTheMoney":false,"impliedVolatility":{"raw":0.7597451393890382,"fmt":"75.97%"},"volume":{"raw":1,"fmt":"1","longFmt":"1"},"ask":{"raw":75.5,"fmt":"75.50"},"contractSymbol":"COIN270115C00580000","lastTradeDate":{"raw":1733154264,"fmt":"2024-12-02","longFmt":"2024-12-02T15:44"},"contractSize":"REGULAR","expiration":{"raw":1799971200,"fmt":"2027-01-15","longFmt":"2027-01-15T00:00"},"currency":"USD","bid":{"raw":71.5,"fmt":"71.50"},"lastPrice":{"raw":77.65,"fmt":"77.65"}},{"percentChange":{"raw":0.0,"fmt":"0.00%"},"openInterest":{"raw":1,"fmt":"1","longFmt":"1"},"change":{"raw":0.0,"fmt":"0.00"},"strike":{"raw":590.0,"fmt":"590.00"},"inTheMoney":false,"impliedVolatility":{"raw":0.7611794512176514,"fmt":"76.12%"},"ask":{"raw":74.5,"fmt":"74.50"},"contractSymbol":"COIN270115C00590000","lastTradeDate":{"raw":1731961847,"fmt":"2024-11-18","longFmt":"2024-11-18T20:30"},"contractSize":"REGULAR","expiration":{"raw":1799971200,"fmt":"2027-01-15","longFmt":"2027-01-15T00:00"},"currency":"USD","bid":{"raw":70.5,"fmt":"70.50"},"lastPrice":{"raw":88.05,"fmt":"88.05"}},{"percentChange":{"raw":0.0,"fmt":"0.00%"},"openInterest":{"raw":9,"fmt":"9","longFmt":"9"},"change":{"raw":0.0,"fmt":"0.00"},"strike":{"raw":600.0,"fmt":"600.00"},"inTheMoney":false,"impliedVolatility":{"raw":0.7625756164550781,"fmt":"76.26%"},"volume":{"raw":2,"fmt":"2","longFmt":"2"},"ask":{"raw":73.0,"fmt":"73.00"},"contractSymbol":"COIN270115C00600000","lastTradeDate":{"raw":1732650683,"fmt":"2024-11-26","longFmt":"2024-11-26T19:51"},"contractSize":"REGULAR","expiration":{"raw":1799971200,"fmt":"2027-01-15","longFmt":"2027-01-15T00:00"},"currency":"USD","bid":{"raw":70.05,"fmt":"70.05"},"lastPrice":{"raw":69.12,"fmt":"69.12"}},{"percentChange":{"raw":0.0,"fmt":"0.00%"},"openInterest":{"raw":2,"fmt":"2","longFmt":"2"},"change":{"raw":0.0,"fmt":"0.00"},"strike":{"raw":610.0,"fmt":"610.00"},"inTheMoney":false,"impliedVolatility":{"raw":0.7592492337036134,"fmt":"75.92%"},"volume":{"raw":1,"fmt":"1","longFmt":"1"},"ask":{"raw":71.5,"fmt":"71.50"},"contractSymbol":"COIN270115C00610000","lastTradeDate":{"raw":1732732633,"fmt":"2024-11-27","longFmt":"2024-11-27T18:37"},"contractSize":"REGULAR","expiration":{"raw":1799971200,"fmt":"2027-01-15","longFmt":"2027-01-15T00:00"},"currency":"USD","bid":{"raw":68.0,"fmt":"68.00"},"lastPrice":{"raw":73.85,"fmt":"73.85"}},{"percentChange":{"raw":0.0,"fmt":"0.00%"},"openInterest":{"raw":4,"fmt":"4","longFmt":"4"},"change":{"raw":0.0,"fmt":"0.00"},"strike":{"raw":630.0,"fmt":"630.00"},"inTheMoney":false,"impliedVolatility":{"raw":0.76407096282959,"fmt":"76.41%"},"volume":{"raw":1,"fmt":"1","longFmt":"1"},"ask":{"raw":69.35,"fmt":"69.35"},"contractSymbol":"COIN270115C00630000","lastTradeDate":{"raw":1732304207,"fmt":"2024-11-22","longFmt":"2024-11-22T19:36"},"contractSize":"REGULAR","expiration":{"raw":1799971200,"fmt":"2027-01-15","longFmt":"2027-01-15T00:00"},"currency":"USD","bid":{"raw":67.25,"fmt":"67.25"},"lastPrice":{"raw":76.74,"fmt":"76.74"}},{"percentChange":{"raw":0.8209703,"fmt":"0.82%"},"openInterest":{"raw":6,"fmt":"6","longFmt":"6"},"change":{"raw":0.5699997,"fmt":"0.57"},"strike":{"raw":640.0,"fmt":"640.00"},"inTheMoney":false,"impliedVolatility":{"raw":0.7628197546386719,"fmt":"76.28%"},"volume":{"raw":15,"fmt":"15","longFmt":"15"},"ask":{"raw":68.0,"fmt":"68.00"},"contractSymbol":"COIN270115C00640000","lastTradeDate":{"raw":1733157146,"fmt":"2024-12-02","longFmt":"2024-12-02T16:32"},"contractSize":"REGULAR","expiration":{"raw":1799971200,"fmt":"2027-01-15","longFmt":"2027-01-15T00:00"},"currency":"USD","bid":{"raw":65.95,"fmt":"65.95"},"lastPrice":{"raw":70.0,"fmt":"70.00"}},{"percentChange":{"raw":0.0,"fmt":"0.00%"},"openInterest":{"raw":20,"fmt":"20","longFmt":"20"},"change":{"raw":0.0,"fmt":"0.00"},"strike":{"raw":650.0,"fmt":"650.00"},"inTheMoney":false,"impliedVolatility":{"raw":0.76299522895813,"fmt":"76.30%"},"volume":{"raw":13,"fmt":"13","longFmt":"13"},"ask":{"raw":67.0,"fmt":"67.00"},"contractSymbol":"COIN270115C00650000","lastTradeDate":{"raw":1732033510,"fmt":"2024-11-19","longFmt":"2024-11-19T16:25"},"contractSize":"REGULAR","expiration":{"raw":1799971200,"fmt":"2027-01-15","longFmt":"2027-01-15T00:00"},"currency":"USD","bid":{"raw":64.85,"fmt":"64.85"},"lastPrice":{"raw":79.08,"fmt":"79.08"}},{"percentChange":{"raw":1.1006361,"fmt":"1.10%"},"openInterest":{"raw":220,"fmt":"220","longFmt":"220"},"change":{"raw":0.7000046,"fmt":"0.70"},"strike":{"raw":660.0,"fmt":"660.00"},"inTheMoney":false,"impliedVolatility":{"raw":0.7631707032775878,"fmt":"76.32%"},"volume":{"raw":3,"fmt":"3","longFmt":"3"},"ask":{"raw":65.9,"fmt":"65.90"},"contractSymbol":"COIN270115C00660000","lastTradeDate":{"raw":1733166268,"fmt":"2024-12-02","longFmt":"2024-12-02T19:04"},"contractSize":"REGULAR","expiration":{"raw":1799971200,"fmt":"2027-01-15","longFmt":"2027-01-15T00:00"},"currency":"USD","bid":{"raw":63.9,"fmt":"63.90"},"lastPrice":{"raw":64.3,"fmt":"64.30"}}],"puts":[{"percentChange":{"raw":1.2141242,"fmt":"1.21%"},"openInterest":{"raw":123,"fmt":"123","longFmt":"123"},"change":{"raw":0.10999966,"fmt":"0.11"},"strike":{"raw":85.0,"fmt":"85.00"},"inTheMoney":false,"impliedVolatility":{"raw":0.7412745599365234,"fmt":"74.13%"},"volume":{"raw":4,"fmt":"4","longFmt":"4"},"ask":{"raw":9.5,"fmt":"9.50"},"contractSymbol":"COIN270115P00085000","lastTradeDate":{"raw":1733172380,"fmt":"2024-12-02","longFmt":"2024-12-02T20:46"},"contractSize":"REGULAR","expiration":{"raw":1799971200,"fmt":"2027-01-15","longFmt":"2027-01-15T00:00"},"currency":"USD","bid":{"raw":9.05,"fmt":"9.05"},"lastPrice":{"raw":9.17,"fmt":"9.17"}},{"percentChange":{"raw":0.0,"fmt":"0.00%"},"openInterest":{"raw":77,"fmt":"77","longFmt":"77"},"change":{"raw":0.0,"fmt":"0.00"},"strike":{"raw":90.0,"fmt":"90.00"},"inTheMoney":false,"impliedVolatility":{"raw":0.7354152435302734,"fmt":"73.54%"},"volume":{"raw":1,"fmt":"1","longFmt":"1"},"ask":{"raw":11.95,"fmt":"11.95"},"contractSymbol":"COIN270115P00090000","lastTradeDate":{"raw":1732029206,"fmt":"2024-11-19","longFmt":"2024-11-19T15:13"},"contractSize":"REGULAR","expiration":{"raw":1799971200,"fmt":"2027-01-15","longFmt":"2027-01-15T00:00"},"currency":"USD","bid":{"raw":8.8,"fmt":"8.80"},"lastPrice":{"raw":10.29,"fmt":"10.29"}},{"percentChange":{"raw":-4.6952276,"fmt":"-4.70%"},"openInterest":{"raw":66,"fmt":"66","longFmt":"66"},"change":{"raw":-0.57000065,"fmt":"-0.57"},"strike":{"raw":95.0,"fmt":"95.00"},"inTheMoney":false,"impliedVolatility":{"raw":0.7297085134887695,"fmt":"72.97%"},"volume":{"raw":1,"fmt":"1","longFmt":"1"},"ask":{"raw":12.6,"fmt":"12.60"},"contractSymbol":"COIN270115P00095000","lastTradeDate":{"raw":1733171538,"fmt":"2024-12-02","longFmt":"2024-12-02T20:32"},"contractSize":"REGULAR","expiration":{"raw":1799971200,"fmt":"2027-01-15","longFmt":"2027-01-15T00:00"},"currency":"USD","bid":{"raw":10.45,"fmt":"10.45"},"lastPrice":{"raw":11.57,"fmt":"11.57"}},{"percentChange":{"raw":0.0,"fmt":"0.00%"},"openInterest":{"raw":91,"fmt":"91","longFmt":"91"},"change":{"raw":0.0,"fmt":"0.00"},"strike":{"raw":100.0,"fmt":"100.00"},"inTheMoney":false,"impliedVolatility":{"raw":0.7201566070556642,"fmt":"72.02%"},"volume":{"raw":1,"fmt":"1","longFmt":"1"},"ask":{"raw":13.15,"fmt":"13.15"},"contractSymbol":"COIN270115P00100000","lastTradeDate":{"raw":1732286704,"fmt":"2024-11-22","longFmt":"2024-11-22T14:45"},"contractSize":"REGULAR","expiration":{"raw":1799971200,"fmt":"2027-01-15","longFmt":"2027-01-15T00:00"},"currency":"USD","bid":{"raw":11.9,"fmt":"11.90"},"lastPrice":{"raw":14.79,"fmt":"14.79"}},{"percentChange":{"raw":0.0,"fmt":"0.00%"},"openInterest":{"raw":47,"fmt":"47","longFmt":"47"},"change":{"raw":0.0,"fmt":"0.00"},"strike":{"raw":105.0,"fmt":"105.00"},"inTheMoney":false,"impliedVolatility":{"raw":0.7163724652099608,"fmt":"71.64%"},"volume":{"raw":1,"fmt":"1","longFmt":"1"},"ask":{"raw":14.55,"fmt":"14.55"},"contractSymbol":"COIN270115P00105000","lastTradeDate":{"raw":1732633160,"fmt":"2024-11-26","longFmt":"2024-11-26T14:59"},"contractSize":"REGULAR","expiration":{"raw":1799971200,"fmt":"2027-01-15","longFmt":"2027-01-15T00:00"},"currency":"USD","bid":{"raw":13.15,"fmt":"13.15"},"lastPrice":{"raw":14.25,"fmt":"14.25"}},{"percentChange":{"raw":-4.6261063,"fmt":"-4.63%"},"openInterest":{"raw":14,"fmt":"14","longFmt":"14"},"change":{"raw":-0.72999954,"fmt":"-0.73"},"strike":{"raw":110.0,"fmt":"110.00"},"inTheMoney":false,"impliedVolatility":{"raw":0.7107878042602539,"fmt":"71.08%"},"volume":{"raw":1,"fmt":"1","longFmt":"1"},"ask":{"raw":15.85,"fmt":"15.85"},"contractSymbol":"COIN270115P00110000","lastTradeDate":{"raw":1733168126,"fmt":"2024-12-02","longFmt":"2024-12-02T19:35"},"contractSize":"REGULAR","expiration":{"raw":1799971200,"fmt":"2027-01-15","longFmt":"2027-01-15T00:00"},"currency":"USD","bid":{"raw":14.4,"fmt":"14.40"},"lastPrice":{"raw":15.05,"fmt":"15.05"}},{"percentChange":{"raw":0.0,"fmt":"0.00%"},"openInterest":{"raw":2,"fmt":"2","longFmt":"2"},"change":{"raw":0.0,"fmt":"0.00"},"strike":{"raw":115.0,"fmt":"115.00"},"inTheMoney":false,"impliedVolatility":{"raw":0.7074309042358399,"fmt":"70.74%"},"volume":{"raw":1,"fmt":"1","longFmt":"1"},"ask":{"raw":17.25,"fmt":"17.25"},"contractSymbol":"COIN270115P00115000","lastTradeDate":{"raw":1731341454,"fmt":"2024-11-11","longFmt":"2024-11-11T16:10"},"contractSize":"REGULAR","expiration":{"raw":1799971200,"fmt":"2027-01-15","longFmt":"2027-01-15T00:00"},"currency":"USD","bid":{"raw":15.9,"fmt":"15.90"},"lastPrice":{"raw":16.05,"fmt":"16.05"}},{"percentChange":{"raw":0.0,"fmt":"0.00%"},"openInterest":{"raw":23,"fmt":"23","longFmt":"23"},"change":{"raw":0.0,"fmt":"0.00"},"strike":{"raw":120.0,"fmt":"120.00"},"inTheMoney":false,"impliedVolatility":{"raw":0.7036772796630859,"fmt":"70.37%"},"volume":{"raw":1,"fmt":"1","longFmt":"1"},"ask":{"raw":18.65,"fmt":"18.65"},"contractSymbol":"COIN270115P00120000","lastTradeDate":{"raw":1732558479,"fmt":"2024-11-25","longFmt":"2024-11-25T18:14"},"contractSize":"REGULAR","expiration":{"raw":1799971200,"fmt":"2027-01-15","longFmt":"2027-01-15T00:00"},"currency":"USD","bid":{"raw":17.45,"fmt":"17.45"},"lastPrice":{"raw":18.35,"fmt":"18.35"}},{"percentChange":{"raw":0.0,"fmt":"0.00%"},"openInterest":{"raw":28,"fmt":"28","longFmt":"28"},"change":{"raw":0.0,"fmt":"0.00"},"strike":{"raw":125.0,"fmt":"125.00"},"inTheMoney":false,"impliedVolatility":{"raw":0.699923655090332,"fmt":"69.99%"},"volume":{"raw":1,"fmt":"1","longFmt":"1"},"ask":{"raw":20.25,"fmt":"20.25"},"contractSymbol":"COIN270115P00125000","lastTradeDate":{"raw":1732901339,"fmt":"2024-11-29","longFmt":"2024-11-29T17:28"},"contractSize":"REGULAR","expiration":{"raw":1799971200,"fmt":"2027-01-15","longFmt":"2027-01-15T00:00"},"currency":"USD","bid":{"raw":18.9,"fmt":"18.90"},"lastPrice":{"raw":19.71,"fmt":"19.71"}},{"percentChange":{"raw":0.0,"fmt":"0.00%"},"openInterest":{"raw":10,"fmt":"10","longFmt":"10"},"change":{"raw":0.0,"fmt":"0.00"},"strike":{"raw":130.0,"fmt":"130.00"},"inTheMoney":false,"impliedVolatility":{"raw":0.6962310650634767,"fmt":"69.62%"},"volume":{"raw":1,"fmt":"1","longFmt":"1"},"ask":{"raw":22.0,"fmt":"22.00"},"contractSymbol":"COIN270115P00130000","lastTradeDate":{"raw":1731342875,"fmt":"2024-11-11","longFmt":"2024-11-11T16:34"},"contractSize":"REGULAR","expiration":{"raw":1799971200,"fmt":"2027-01-15","longFmt":"2027-01-15T00:00"},"currency":"USD","bid":{"raw":20.3,"fmt":"20.30"},"lastPrice":{"raw":21.73,"fmt":"21.73"}},{"percentChange":{"raw":0.0,"fmt":"0.00%"},"openInterest":{"raw":21,"fmt":"21","longFmt":"21"},"change":{"raw":0.0,"fmt":"0.00"},"strike":{"raw":135.0,"fmt":"135.00"},"inTheMoney":false,"impliedVolatility":{"raw":0.6925995095825196,"fmt":"69.26%"},"volume":{"raw":1,"fmt":"1","longFmt":"1"},"ask":{"raw":23.75,"fmt":"23.75"},"contractSymbol":"COIN270115P00135000","lastTradeDate":{"raw":1732650917,"fmt":"2024-11-26","longFmt":"2024-11-26T19:55"},"contractSize":"REGULAR","expiration":{"raw":1799971200,"fmt":"2027-01-15","longFmt":"2027-01-15T00:00"},"currency":"USD","bid":{"raw":21.8,"fmt":"21.80"},"lastPrice":{"raw":24.0,"fmt":"24.00"}},{"percentChange":{"raw":0.0,"fmt":"0.00%"},"openInterest":{"raw":19,"fmt":"19","longFmt":"19"},"change":{"raw":0.0,"fmt":"0.00"},"strike":{"raw":140.0,"fmt":"140.00"},"inTheMoney":false,"impliedVolatility":{"raw":0.6915924395751953,"fmt":"69.16%"},"volume":{"raw":1,"fmt":"1","longFmt":"1"},"ask":{"raw":25.55,"fmt":"25.55"},"contractSymbol":"COIN270115P00140000","lastTradeDate":{"raw":1732729929,"fmt":"2024-11-27","longFmt":"2024-11-27T17:52"},"contractSize":"REGULAR","expiration":{"raw":1799971200,"fmt":"2027-01-15","longFmt":"2027-01-15T00:00"},"currency":"USD","bid":{"raw":23.75,"fmt":"23.75"},"lastPrice":{"raw":25.5,"fmt":"25.50"}},{"percentChange":{"raw":0.0,"fmt":"0.00%"},"openInterest":{"raw":49,"fmt":"49","longFmt":"49"},"change":{"raw":0.0,"fmt":"0.00"},"strike":{"raw":145.0,"fmt":"145.00"},"inTheMoney":false,"impliedVolatility":{"raw":0.6864807963562012,"fmt":"68.65%"},"volume":{"raw":1,"fmt":"1","longFmt":"1"},"ask":{"raw":27.25,"fmt":"27.25"},"contractSymbol":"COIN270115P00145000","lastTradeDate":{"raw":1732652468,"fmt":"2024-11-26","longFmt":"2024-11-26T20:21"},"contractSize":"REGULAR","expiration":{"raw":1799971200,"fmt":"2027-01-15","longFmt":"2027-01-15T00:00"},"currency":"USD","bid":{"raw":25.25,"fmt":"25.25"},"lastPrice":{"raw":27.59,"fmt":"27.59"}},{"percentChange":{"raw":0.0,"fmt":"0.00%"},"openInterest":{"raw":131,"fmt":"131","longFmt":"131"},"change":{"raw":0.0,"fmt":"0.00"},"strike":{"raw":150.0,"fmt":"150.00"},"inTheMoney":false,"impliedVolatility":{"raw":0.6786531158447267,"fmt":"67.87%"},"volume":{"raw":1,"fmt":"1","longFmt":"1"},"ask":{"raw":28.7,"fmt":"28.70"},"contractSymbol":"COIN270115P00150000","lastTradeDate":{"raw":1732901312,"fmt":"2024-11-29","longFmt":"2024-11-29T17:28"},"contractSize":"REGULAR","expiration":{"raw":1799971200,"fmt":"2027-01-15","longFmt":"2027-01-15T00:00"},"currency":"USD","bid":{"raw":26.6,"fmt":"26.60"},"lastPrice":{"raw":28.5,"fmt":"28.50"}},{"percentChange":{"raw":0.0,"fmt":"0.00%"},"openInterest":{"raw":36,"fmt":"36","longFmt":"36"},"change":{"raw":0.0,"fmt":"0.00"},"strike":{"raw":155.0,"fmt":"155.00"},"inTheMoney":false,"impliedVolatility":{"raw":0.6746095771789553,"fmt":"67.46%"},"volume":{"raw":5,"fmt":"5","longFmt":"5"},"ask":{"raw":30.7,"fmt":"30.70"},"contractSymbol":"COIN270115P00155000","lastTradeDate":{"raw":1731515756,"fmt":"2024-11-13","longFmt":"2024-11-13T16:35"},"contractSize":"REGULAR","expiration":{"raw":1799971200,"fmt":"2027-01-15","longFmt":"2027-01-15T00:00"},"currency":"USD","bid":{"raw":28.1,"fmt":"28.10"},"lastPrice":{"raw":29.72,"fmt":"29.72"}},{"percentChange":{"raw":0.0,"fmt":"0.00%"},"openInterest":{"raw":75,"fmt":"75","longFmt":"75"},"change":{"raw":0.0,"fmt":"0.00"},"strike":{"raw":160.0,"fmt":"160.00"},"inTheMoney":false,"impliedVolatility":{"raw":0.6786225985717774,"fmt":"67.86%"},"volume":{"raw":13,"fmt":"13","longFmt":"13"},"ask":{"raw":32.7,"fmt":"32.70"},"contractSymbol":"COIN270115P00160000","lastTradeDate":{"raw":1732132209,"fmt":"2024-11-20","longFmt":"2024-11-20T19:50"},"contractSize":"REGULAR","expiration":{"raw":1799971200,"fmt":"2027-01-15","longFmt":"2027-01-15T00:00"},"currency":"USD","bid":{"raw":31.15,"fmt":"31.15"},"lastPrice":{"raw":33.05,"fmt":"33.05"}},{"percentChange":{"raw":0.0,"fmt":"0.00%"},"openInterest":{"raw":9,"fmt":"9","longFmt":"9"},"change":{"raw":0.0,"fmt":"0.00"},"strike":{"raw":165.0,"fmt":"165.00"},"inTheMoney":false,"impliedVolatility":{"raw":0.6772188040161133,"fmt":"67.72%"},"volume":{"raw":1,"fmt":"1","longFmt":"1"},"ask":{"raw":34.95,"fmt":"34.95"},"contractSymbol":"COIN270115P00165000","lastTradeDate":{"raw":1731442337,"fmt":"2024-11-12","longFmt":"2024-11-12T20:12"},"contractSize":"REGULAR","expiration":{"raw":1799971200,"fmt":"2027-01-15","longFmt":"2027-01-15T00:00"},"currency":"USD","bid":{"raw":33.1,"fmt":"33.10"},"lastPrice":{"raw":32.15,"fmt":"32.15"}},{"percentChange":{"raw":0.0,"fmt":"0.00%"},"openInterest":{"raw":14,"fmt":"14","longFmt":"14"},"change":{"raw":0.0,"fmt":"0.00"},"strike":{"raw":170.0,"fmt":"170.00"},"inTheMoney":false,"impliedVolatility":{"raw":0.6735109553527834,"fmt":"67.35%"},"volume":{"raw":1,"fmt":"1","longFmt":"1"},"ask":{"raw":36.7,"fmt":"36.70"},"contractSymbol":"COIN270115P00170000","lastTradeDate":{"raw":1731942219,"fmt":"2024-11-18","longFmt":"2024-11-18T15:03"},"contractSize":"REGULAR","expiration":{"raw":1799971200,"fmt":"2027-01-15","longFmt":"2027-01-15T00:00"},"currency":"USD","bid":{"raw":35.2,"fmt":"35.20"},"lastPrice":{"raw":37.65,"fmt":"37.65"}},{"percentChange":{"raw":0.0,"fmt":"0.00%"},"openInterest":{"raw":7,"fmt":"7","longFmt":"7"},"change":{"raw":0.0,"fmt":"0.00"},"strike":{"raw":175.0,"fmt":"175.00"},"inTheMoney":false,"impliedVolatility":{"raw":0.6760896649169923,"fmt":"67.61%"},"volume":{"raw":1,"fmt":"1","longFmt":"1"},"ask":{"raw":39.8,"fmt":"39.80"},"contractSymbol":"COIN270115P00175000","lastTradeDate":{"raw":1732553845,"fmt":"2024-11-25","longFmt":"2024-11-25T16:57"},"contractSize":"REGULAR","expiration":{"raw":1799971200,"fmt":"2027-01-15","longFmt":"2027-01-15T00:00"},"currency":"USD","bid":{"raw":37.3,"fmt":"37.30"},"lastPrice":{"raw":38.6,"fmt":"38.60"}},{"percentChange":{"raw":0.0,"fmt":"0.00%"},"openInterest":{"raw":39,"fmt":"39","longFmt":"39"},"change":{"raw":0.0,"fmt":"0.00"},"strike":{"raw":180.0,"fmt":"180.00"},"inTheMoney":false,"impliedVolatility":{"raw":0.6700930207824709,"fmt":"67.01%"},"volume":{"raw":1,"fmt":"1","longFmt":"1"},"ask":{"raw":41.0,"fmt":"41.00"},"contractSymbol":"COIN270115P00180000","lastTradeDate":{"raw":1732651836,"fmt":"2024-11-26","longFmt":"2024-11-26T20:10"},"contractSize":"REGULAR","expiration":{"raw":1799971200,"fmt":"2027-01-15","longFmt":"2027-01-15T00:00"},"currency":"USD","bid":{"raw":39.65,"fmt":"39.65"},"lastPrice":{"raw":41.5,"fmt":"41.50"}},{"percentChange":{"raw":0.0,"fmt":"0.00%"},"openInterest":{"raw":1,"fmt":"1","longFmt":"1"},"change":{"raw":0.0,"fmt":"0.00"},"strike":{"raw":185.0,"fmt":"185.00"},"inTheMoney":false,"impliedVolatility":{"raw":0.6683077603149415,"fmt":"66.83%"},"volume":{"raw":1,"fmt":"1","longFmt":"1"},"ask":{"raw":43.25,"fmt":"43.25"},"contractSymbol":"COIN270115P00185000","lastTradeDate":{"raw":1730822127,"fmt":"2024-11-05","longFmt":"2024-11-05T15:55"},"contractSize":"REGULAR","expiration":{"raw":1799971200,"fmt":"2027-01-15","longFmt":"2027-01-15T00:00"},"currency":"USD","bid":{"raw":41.9,"fmt":"41.90"},"lastPrice":{"raw":62.35,"fmt":"62.35"}},{"percentChange":{"raw":0.0,"fmt":"0.00%"},"openInterest":{"raw":13,"fmt":"13","longFmt":"13"},"change":{"raw":0.0,"fmt":"0.00"},"strike":{"raw":190.0,"fmt":"190.00"},"inTheMoney":false,"impliedVolatility":{"raw":0.6656832748413087,"fmt":"66.57%"},"volume":{"raw":1,"fmt":"1","longFmt":"1"},"ask":{"raw":45.5,"fmt":"45.50"},"contractSymbol":"COIN270115P00190000","lastTradeDate":{"raw":1732724100,"fmt":"2024-11-27","longFmt":"2024-11-27T16:15"},"contractSize":"REGULAR","expiration":{"raw":1799971200,"fmt":"2027-01-15","longFmt":"2027-01-15T00:00"},"currency":"USD","bid":{"raw":44.05,"fmt":"44.05"},"lastPrice":{"raw":45.9,"fmt":"45.90"}},{"percentChange":{"raw":0.0,"fmt":"0.00%"},"openInterest":{"raw":21,"fmt":"21","longFmt":"21"},"change":{"raw":0.0,"fmt":"0.00"},"strike":{"raw":195.0,"fmt":"195.00"},"inTheMoney":false,"impliedVolatility":{"raw":0.6624789611816408,"fmt":"66.25%"},"volume":{"raw":1,"fmt":"1","longFmt":"1"},"ask":{"raw":47.7,"fmt":"47.70"},"contractSymbol":"COIN270115P00195000","lastTradeDate":{"raw":1732635320,"fmt":"2024-11-26","longFmt":"2024-11-26T15:35"},"contractSize":"REGULAR","expiration":{"raw":1799971200,"fmt":"2027-01-15","longFmt":"2027-01-15T00:00"},"currency":"USD","bid":{"raw":46.2,"fmt":"46.20"},"lastPrice":{"raw":47.26,"fmt":"47.26"}},{"percentChange":{"raw":0.0,"fmt":"0.00%"},"openInterest":{"raw":83,"fmt":"83","longFmt":"83"},"change":{"raw":0.0,"fmt":"0.00"},"strike":{"raw":200.0,"fmt":"200.00"},"inTheMoney":false,"impliedVolatility":{"raw":0.6622043057250978,"fmt":"66.22%"},"volume":{"raw":4,"fmt":"4","longFmt":"4"},"ask":{"raw":50.1,"fmt":"50.10"},"contractSymbol":"COIN270115P00200000","lastTradeDate":{"raw":1732901268,"fmt":"2024-11-29","longFmt":"2024-11-29T17:27"},"contractSize":"REGULAR","expiration":{"raw":1799971200,"fmt":"2027-01-15","longFmt":"2027-01-15T00:00"},"currency":"USD","bid":{"raw":48.9,"fmt":"48.90"},"lastPrice":{"raw":50.25,"fmt":"50.25"}},{"percentChange":{"raw":-5.787154,"fmt":"-5.79%"},"openInterest":{"raw":39,"fmt":"39","longFmt":"39"},"change":{"raw":-3.289997,"fmt":"-3.29"},"strike":{"raw":210.0,"fmt":"210.00"},"inTheMoney":false,"impliedVolatility":{"raw":0.6557041265869141,"fmt":"65.57%"},"volume":{"raw":1,"fmt":"1","longFmt":"1"},"ask":{"raw":54.75,"fmt":"54.75"},"contractSymbol":"COIN270115P00210000","lastTradeDate":{"raw":1733153423,"fmt":"2024-12-02","longFmt":"2024-12-02T15:30"},"contractSize":"REGULAR","expiration":{"raw":1799971200,"fmt":"2027-01-15","longFmt":"2027-01-15T00:00"},"currency":"USD","bid":{"raw":53.3,"fmt":"53.30"},"lastPrice":{"raw":53.56,"fmt":"53.56"}},{"percentChange":{"raw":-6.5705166,"fmt":"-6.57%"},"openInterest":{"raw":30,"fmt":"30","longFmt":"30"},"change":{"raw":-4.1000023,"fmt":"-4.10"},"strike":{"raw":220.0,"fmt":"220.00"},"inTheMoney":false,"impliedVolatility":{"raw":0.6539036074829102,"fmt":"65.39%"},"volume":{"raw":2,"fmt":"2","longFmt":"2"},"ask":{"raw":59.8,"fmt":"59.80"},"contractSymbol":"COIN270115P00220000","lastTradeDate":{"raw":1733156585,"fmt":"2024-12-02","longFmt":"2024-12-02T16:23"},"contractSize":"REGULAR","expiration":{"raw":1799971200,"fmt":"2027-01-15","longFmt":"2027-01-15T00:00"},"currency":"USD","bid":{"raw":58.75,"fmt":"58.75"},"lastPrice":{"raw":58.3,"fmt":"58.30"}},{"percentChange":{"raw":0.20475233,"fmt":"0.20%"},"openInterest":{"raw":54,"fmt":"54","longFmt":"54"},"change":{"raw":0.12999725,"fmt":"0.13"},"strike":{"raw":230.0,"fmt":"230.00"},"inTheMoney":false,"impliedVolatility":{"raw":0.6521336056518555,"fmt":"65.21%"},"volume":{"raw":2,"fmt":"2","longFmt":"2"},"ask":{"raw":65.4,"fmt":"65.40"},"contractSymbol":"COIN270115P00230000","lastTradeDate":{"raw":1733159816,"fmt":"2024-12-02","longFmt":"2024-12-02T17:16"},"contractSize":"REGULAR","expiration":{"raw":1799971200,"fmt":"2027-01-15","longFmt":"2027-01-15T00:00"},"currency":"USD","bid":{"raw":64.0,"fmt":"64.00"},"lastPrice":{"raw":63.62,"fmt":"63.62"}},{"percentChange":{"raw":0.0,"fmt":"0.00%"},"openInterest":{"raw":43,"fmt":"43","longFmt":"43"},"change":{"raw":0.0,"fmt":"0.00"},"strike":{"raw":240.0,"fmt":"240.00"},"inTheMoney":false,"impliedVolatility":{"raw":0.646411616973877,"fmt":"64.64%"},"volume":{"raw":1,"fmt":"1","longFmt":"1"},"ask":{"raw":70.5,"fmt":"70.50"},"contractSymbol":"COIN270115P00240000","lastTradeDate":{"raw":1732724291,"fmt":"2024-11-27","longFmt":"2024-11-27T16:18"},"contractSize":"REGULAR","expiration":{"raw":1799971200,"fmt":"2027-01-15","longFmt":"2027-01-15T00:00"},"currency":"USD","bid":{"raw":69.0,"fmt":"69.00"},"lastPrice":{"raw":72.11,"fmt":"72.11"}},{"percentChange":{"raw":-4.2866263,"fmt":"-4.29%"},"openInterest":{"raw":21,"fmt":"21","longFmt":"21"},"change":{"raw":-3.3499985,"fmt":"-3.35"},"strike":{"raw":250.0,"fmt":"250.00"},"inTheMoney":false,"impliedVolatility":{"raw":0.6446263565063476,"fmt":"64.46%"},"volume":{"raw":1,"fmt":"1","longFmt":"1"},"ask":{"raw":76.2,"fmt":"76.20"},"contractSymbol":"COIN270115P00250000","lastTradeDate":{"raw":1733160916,"fmt":"2024-12-02","longFmt":"2024-12-02T17:35"},"contractSize":"REGULAR","expiration":{"raw":1799971200,"fmt":"2027-01-15","longFmt":"2027-01-15T00:00"},"currency":"USD","bid":{"raw":74.75,"fmt":"74.75"},"lastPrice":{"raw":74.8,"fmt":"74.80"}},{"percentChange":{"raw":0.024611253,"fmt":"0.02%"},"openInterest":{"raw":54,"fmt":"54","longFmt":"54"},"change":{"raw":0.019996643,"fmt":"0.02"},"strike":{"raw":260.0,"fmt":"260.00"},"inTheMoney":false,"impliedVolatility":{"raw":0.6412847151184082,"fmt":"64.13%"},"volume":{"raw":1,"fmt":"1","longFmt":"1"},"ask":{"raw":81.85,"fmt":"81.85"},"contractSymbol":"COIN270115P00260000","lastTradeDate":{"raw":1733169814,"fmt":"2024-12-02","longFmt":"2024-12-02T20:03"},"contractSize":"REGULAR","expiration":{"raw":1799971200,"fmt":"2027-01-15","longFmt":"2027-01-15T00:00"},"currency":"USD","bid":{"raw":80.4,"fmt":"80.40"},"lastPrice":{"raw":81.27,"fmt":"81.27"}},{"percentChange":{"raw":0.0,"fmt":"0.00%"},"openInterest":{"raw":22,"fmt":"22","longFmt":"22"},"change":{"raw":0.0,"fmt":"0.00"},"strike":{"raw":270.0,"fmt":"270.00"},"inTheMoney":false,"impliedVolatility":{"raw":0.6397588514709474,"fmt":"63.98%"},"volume":{"raw":11,"fmt":"11","longFmt":"11"},"ask":{"raw":87.7,"fmt":"87.70"},"contractSymbol":"COIN270115P00270000","lastTradeDate":{"raw":1732134976,"fmt":"2024-11-20","longFmt":"2024-11-20T20:36"},"contractSize":"REGULAR","expiration":{"raw":1799971200,"fmt":"2027-01-15","longFmt":"2027-01-15T00:00"},"currency":"USD","bid":{"raw":86.65,"fmt":"86.65"},"lastPrice":{"raw":87.97,"fmt":"87.97"}},{"percentChange":{"raw":0.0,"fmt":"0.00%"},"openInterest":{"raw":26,"fmt":"26","longFmt":"26"},"change":{"raw":0.0,"fmt":"0.00"},"strike":{"raw":280.0,"fmt":"280.00"},"inTheMoney":false,"impliedVolatility":{"raw":0.6424443714904786,"fmt":"64.24%"},"volume":{"raw":1,"fmt":"1","longFmt":"1"},"ask":{"raw":96.0,"fmt":"96.00"},"contractSymbol":"COIN270115P00280000","lastTradeDate":{"raw":1732204594,"fmt":"2024-11-21","longFmt":"2024-11-21T15:56"},"contractSize":"REGULAR","expiration":{"raw":1799971200,"fmt":"2027-01-15","longFmt":"2027-01-15T00:00"},"currency":"USD","bid":{"raw":92.0,"fmt":"92.00"},"lastPrice":{"raw":99.85,"fmt":"99.85"}},{"percentChange":{"raw":0.0,"fmt":"0.00%"},"openInterest":{"raw":74,"fmt":"74","longFmt":"74"},"change":{"raw":0.0,"fmt":"0.00"},"strike":{"raw":290.0,"fmt":"290.00"},"inTheMoney":false,"impliedVolatility":{"raw":0.6353567348480225,"fmt":"63.54%"},"volume":{"raw":1,"fmt":"1","longFmt":"1"},"ask":{"raw":100.8,"fmt":"100.80"},"contractSymbol":"COIN270115P00290000","lastTradeDate":{"raw":1732545193,"fmt":"2024-11-25","longFmt":"2024-11-25T14:33"},"contractSize":"REGULAR","expiration":{"raw":1799971200,"fmt":"2027-01-15","longFmt":"2027-01-15T00:00"},"currency":"USD","bid":{"raw":98.15,"fmt":"98.15"},"lastPrice":{"raw":101.5,"fmt":"101.50"}},{"percentChange":{"raw":-3.2561169,"fmt":"-3.26%"},"openInterest":{"raw":56,"fmt":"56","longFmt":"56"},"change":{"raw":-3.5,"fmt":"-3.50"},"strike":{"raw":300.0,"fmt":"300.00"},"inTheMoney":false,"impliedVolatility":{"raw":0.6329229823303224,"fmt":"63.29%"},"volume":{"raw":1,"fmt":"1","longFmt":"1"},"ask":{"raw":107.1,"fmt":"107.10"},"contractSymbol":"COIN270115P00300000","lastTradeDate":{"raw":1733155628,"fmt":"2024-12-02","longFmt":"2024-12-02T16:07"},"contractSize":"REGULAR","expiration":{"raw":1799971200,"fmt":"2027-01-15","longFmt":"2027-01-15T00:00"},"currency":"USD","bid":{"raw":104.45,"fmt":"104.45"},"lastPrice":{"raw":103.99,"fmt":"103.99"}},{"percentChange":{"raw":0.0,"fmt":"0.00%"},"openInterest":{"raw":45,"fmt":"45","longFmt":"45"},"change":{"raw":0.0,"fmt":"0.00"},"strike":{"raw":310.0,"fmt":"310.00"},"inTheMoney":true,"impliedVolatility":{"raw":0.6311529804992677,"fmt":"63.12%"},"volume":{"raw":1,"fmt":"1","longFmt":"1"},"ask":{"raw":114.0,"fmt":"114.00"},"contractSymbol":"COIN270115P00310000","lastTradeDate":{"raw":1732307483,"fmt":"2024-11-22","longFmt":"2024-11-22T20:31"},"contractSize":"REGULAR","expiration":{"raw":1799971200,"fmt":"2027-01-15","longFmt":"2027-01-15T00:00"},"currency":"USD","bid":{"raw":110.6,"fmt":"110.60"},"lastPrice":{"raw":113.62,"fmt":"113.62"}},{"percentChange":{"raw":0.0,"fmt":"0.00%"},"openInterest":{"raw":40,"fmt":"40","longFmt":"40"},"change":{"raw":0.0,"fmt":"0.00"},"strike":{"raw":320.0,"fmt":"320.00"},"inTheMoney":true,"impliedVolatility":{"raw":0.6295965995788575,"fmt":"62.96%"},"volume":{"raw":10,"fmt":"10","longFmt":"10"},"ask":{"raw":120.9,"fmt":"120.90"},"contractSymbol":"COIN270115P00320000","lastTradeDate":{"raw":1732720725,"fmt":"2024-11-27","longFmt":"2024-11-27T15:18"},"contractSize":"REGULAR","expiration":{"raw":1799971200,"fmt":"2027-01-15","longFmt":"2027-01-15T00:00"},"currency":"USD","bid":{"raw":117.05,"fmt":"117.05"},"lastPrice":{"raw":118.31,"fmt":"118.31"}},{"percentChange":{"raw":-1.0521284,"fmt":"-1.05%"},"openInterest":{"raw":35,"fmt":"35","longFmt":"35"},"change":{"raw":-1.3100052,"fmt":"-1.31"},"strike":{"raw":330.0,"fmt":"330.00"},"inTheMoney":true,"impliedVolatility":{"raw":0.623577067489624,"fmt":"62.36%"},"volume":{"raw":1,"fmt":"1","longFmt":"1"},"ask":{"raw":126.55,"fmt":"126.55"},"contractSymbol":"COIN270115P00330000","lastTradeDate":{"raw":1733153728,"fmt":"2024-12-02","longFmt":"2024-12-02T15:35"},"contractSize":"REGULAR","expiration":{"raw":1799971200,"fmt":"2027-01-15","longFmt":"2027-01-15T00:00"},"currency":"USD","bid":{"raw":123.5,"fmt":"123.50"},"lastPrice":{"raw":123.2,"fmt":"123.20"}},{"percentChange":{"raw":0.0,"fmt":"0.00%"},"openInterest":{"raw":25,"fmt":"25","longFmt":"25"},"change":{"raw":0.0,"fmt":"0.00"},"strike":{"raw":340.0,"fmt":"340.00"},"inTheMoney":true,"impliedVolatility":{"raw":0.6240653438568116,"fmt":"62.41%"},"ask":{"raw":134.5,"fmt":"134.50"},"contractSymbol":"COIN270115P00340000","lastTradeDate":{"raw":1731350708,"fmt":"2024-11-11","longFmt":"2024-11-11T18:45"},"contractSize":"REGULAR","expiration":{"raw":1799971200,"fmt":"2027-01-15","longFmt":"2027-01-15T00:00"},"currency":"USD","bid":{"raw":130.0,"fmt":"130.00"},"lastPrice":{"raw":122.55,"fmt":"122.55"}},{"percentChange":{"raw":0.0,"fmt":"0.00%"},"openInterest":{"raw":58,"fmt":"58","longFmt":"58"},"change":{"raw":0.0,"fmt":"0.00"},"strike":{"raw":350.0,"fmt":"350.00"},"inTheMoney":true,"impliedVolatility":{"raw":0.6203346072387697,"fmt":"62.03%"},"volume":{"raw":1,"fmt":"1","longFmt":"1"},"ask":{"raw":140.6,"fmt":"140.60"},"contractSymbol":"COIN270115P00350000","lastTradeDate":{"raw":1732547560,"fmt":"2024-11-25","longFmt":"2024-11-25T15:12"},"contractSize":"REGULAR","expiration":{"raw":1799971200,"fmt":"2027-01-15","longFmt":"2027-01-15T00:00"},"currency":"USD","bid":{"raw":137.15,"fmt":"137.15"},"lastPrice":{"raw":144.5,"fmt":"144.50"}},{"percentChange":{"raw":-2.2668,"fmt":"-2.27%"},"openInterest":{"raw":30,"fmt":"30","longFmt":"30"},"change":{"raw":-3.3899994,"fmt":"-3.39"},"strike":{"raw":360.0,"fmt":"360.00"},"inTheMoney":true,"impliedVolatility":{"raw":0.6154671022033693,"fmt":"61.55%"},"volume":{"raw":2,"fmt":"2","longFmt":"2"},"ask":{"raw":146.75,"fmt":"146.75"},"contractSymbol":"COIN270115P00360000","lastTradeDate":{"raw":1733151459,"fmt":"2024-12-02","longFmt":"2024-12-02T14:57"},"contractSize":"REGULAR","expiration":{"raw":1799971200,"fmt":"2027-01-15","longFmt":"2027-01-15T00:00"},"currency":"USD","bid":{"raw":144.05,"fmt":"144.05"},"lastPrice":{"raw":146.16,"fmt":"146.16"}},{"percentChange":{"raw":0.0,"fmt":"0.00%"},"openInterest":{"raw":9,"fmt":"9","longFmt":"9"},"change":{"raw":0.0,"fmt":"0.00"},"strike":{"raw":370.0,"fmt":"370.00"},"inTheMoney":true,"impliedVolatility":{"raw":0.6149177912902832,"fmt":"61.49%"},"volume":{"raw":1,"fmt":"1","longFmt":"1"},"ask":{"raw":155.0,"fmt":"155.00"},"contractSymbol":"COIN270115P00370000","lastTradeDate":{"raw":1732652007,"fmt":"2024-11-26","longFmt":"2024-11-26T20:13"},"contractSize":"REGULAR","expiration":{"raw":1799971200,"fmt":"2027-01-15","longFmt":"2027-01-15T00:00"},"currency":"USD","bid":{"raw":150.5,"fmt":"150.50"},"lastPrice":{"raw":157.06,"fmt":"157.06"}},{"percentChange":{"raw":0.0,"fmt":"0.00%"},"openInterest":{"raw":4,"fmt":"4","longFmt":"4"},"change":{"raw":0.0,"fmt":"0.00"},"strike":{"raw":380.0,"fmt":"380.00"},"inTheMoney":true,"impliedVolatility":{"raw":0.6091805439758302,"fmt":"60.92%"},"volume":{"raw":3,"fmt":"3","longFmt":"3"},"ask":{"raw":160.6,"fmt":"160.60"},"contractSymbol":"COIN270115P00380000","lastTradeDate":{"raw":1731348684,"fmt":"2024-11-11","longFmt":"2024-11-11T18:11"},"contractSize":"REGULAR","expiration":{"raw":1799971200,"fmt":"2027-01-15","longFmt":"2027-01-15T00:00"},"currency":"USD","bid":{"raw":158.0,"fmt":"158.00"},"lastPrice":{"raw":150.28,"fmt":"150.28"}},{"percentChange":{"raw":0.0,"fmt":"0.00%"},"openInterest":{"raw":9,"fmt":"9","longFmt":"9"},"change":{"raw":0.0,"fmt":"0.00"},"strike":{"raw":400.0,"fmt":"400.00"},"inTheMoney":true,"impliedVolatility":{"raw":0.602192088470459,"fmt":"60.22%"},"volume":{"raw":6,"fmt":"6","longFmt":"6"},"ask":{"raw":174.85,"fmt":"174.85"},"contractSymbol":"COIN270115P00400000","lastTradeDate":{"raw":1732560853,"fmt":"2024-11-25","longFmt":"2024-11-25T18:54"},"contractSize":"REGULAR","expiration":{"raw":1799971200,"fmt":"2027-01-15","longFmt":"2027-01-15T00:00"},"currency":"USD","bid":{"raw":172.0,"fmt":"172.00"},"lastPrice":{"raw":172.8,"fmt":"172.80"}},{"percentChange":{"raw":0.0,"fmt":"0.00%"},"openInterest":{"raw":1,"fmt":"1","longFmt":"1"},"change":{"raw":0.0,"fmt":"0.00"},"strike":{"raw":450.0,"fmt":"450.00"},"inTheMoney":true,"impliedVolatility":{"raw":0.5907633697509767,"fmt":"59.08%"},"ask":{"raw":212.6,"fmt":"212.60"},"contractSymbol":"COIN270115P00450000","lastTradeDate":{"raw":1731956299,"fmt":"2024-11-18","longFmt":"2024-11-18T18:58"},"contractSize":"REGULAR","expiration":{"raw":1799971200,"fmt":"2027-01-15","longFmt":"2027-01-15T00:00"},"currency":"USD","bid":{"raw":209.75,"fmt":"209.75"},"lastPrice":{"raw":207.61,"fmt":"207.61"}},{"percentChange":{"raw":0.0,"fmt":"0.00%"},"openInterest":{"raw":36,"fmt":"36","longFmt":"36"},"change":{"raw":0.0,"fmt":"0.00"},"strike":{"raw":500.0,"fmt":"500.00"},"inTheMoney":true,"impliedVolatility":{"raw":0.5826457751464844,"fmt":"58.26%"},"volume":{"raw":25,"fmt":"25","longFmt":"25"},"ask":{"raw":253.5,"fmt":"253.50"},"contractSymbol":"COIN270115P00500000","lastTradeDate":{"raw":1732114489,"fmt":"2024-11-20","longFmt":"2024-11-20T14:54"},"contractSize":"REGULAR","expiration":{"raw":1799971200,"fmt":"2027-01-15","longFmt":"2027-01-15T00:00"},"currency":"USD","bid":{"raw":249.0,"fmt":"249.00"},"lastPrice":{"raw":244.0,"fmt":"244.00"}},{"percentChange":{"raw":0.0,"fmt":"0.00%"},"openInterest":{"raw":0,"fmt":"0","longFmt":"0"},"change":{"raw":0.0,"fmt":"0.00"},"strike":{"raw":610.0,"fmt":"610.00"},"inTheMoney":true,"impliedVolatility":{"raw":0.5568891967773439,"fmt":"55.69%"},"ask":{"raw":345.0,"fmt":"345.00"},"contractSymbol":"COIN270115P00610000","lastTradeDate":{"raw":1731514586,"fmt":"2024-11-13","longFmt":"2024-11-13T16:16"},"contractSize":"REGULAR","expiration":{"raw":1799971200,"fmt":"2027-01-15","longFmt":"2027-01-15T00:00"},"currency":"USD","bid":{"raw":341.0,"fmt":"341.00"},"lastPrice":{"raw":333.01,"fmt":"333.01"}},{"percentChange":{"raw":0.0,"fmt":"0.00%"},"openInterest":{"raw":1,"fmt":"1","longFmt":"1"},"change":{"raw":0.0,"fmt":"0.00"},"strike":{"raw":620.0,"fmt":"620.00"},"inTheMoney":true,"impliedVolatility":{"raw":0.5569197140502932,"fmt":"55.69%"},"ask":{"raw":354.0,"fmt":"354.00"},"contractSymbol":"COIN270115P00620000","lastTradeDate":{"raw":1731508958,"fmt":"2024-11-13","longFmt":"2024-11-13T14:42"},"contractSize":"REGULAR","expiration":{"raw":1799971200,"fmt":"2027-01-15","longFmt":"2027-01-15T00:00"},"currency":"USD","bid":{"raw":350.0,"fmt":"350.00"},"lastPrice":{"raw":336.38,"fmt":"336.38"}},{"percentChange":{"raw":0.0,"fmt":"0.00%"},"openInterest":{"raw":24,"fmt":"24","longFmt":"24"},"change":{"raw":0.0,"fmt":"0.00"},"strike":{"raw":660.0,"fmt":"660.00"},"inTheMoney":true,"impliedVolatility":{"raw":0.5481459980773928,"fmt":"54.81%"},"volume":{"raw":2,"fmt":"2","longFmt":"2"},"ask":{"raw":389.0,"fmt":"389.00"},"contractSymbol":"COIN270115P00660000","lastTradeDate":{"raw":1732902762,"fmt":"2024-11-29","longFmt":"2024-11-29T17:52"},"contractSize":"REGULAR","expiration":{"raw":1799971200,"fmt":"2027-01-15","longFmt":"2027-01-15T00:00"},"currency":"USD","bid":{"raw":385.0,"fmt":"385.00"},"lastPrice":{"raw":388.5,"fmt":"388.50"}}]}]}],"error":null}}